{"connect":{"statusCode":200,"response":{"id":"","name":"coinnest","private":false,"enableRateLimit":true,"countries":["KR"],"rateLimit":1000,"has":{"cancelAllOrders":"false","cancelOrder":"true","cancelOrders":"false","CORS":"false","createDepositAddress":"false","createLimitOrder":"true","createMarketOrder":"true","createOrder":"true","deposit":"false","editOrder":"emulated","fetchBalance":"true","fetchBidsAsks":"false","fetchClosedOrders":"false","fetchCurrencies":"false","fetchDepositAddress":"false","fetchDeposits":"false","fetchFundingFees":"false","fetchL2OrderBook":"true","fetchLedger":"false","fetchMarkets":"true","fetchMyTrades":"false","fetchOHLCV":"emulated","fetchOpenOrders":"true","fetchOrder":"false","fetchOrderBook":"true","fetchOrderBooks":"false","fetchOrders":"false","fetchTicker":"true","fetchTickers":"false","fetchTrades":"true","fetchTradingFee":"false","fetchTradingFees":"false","fetchTradingLimits":"false","fetchTransactions":"false","fetchWithdrawals":"false","privateAPI":"true","publicAPI":"true","withdraw":"false"},"urls":{"logo":"https://user-images.githubusercontent.com/1294454/38065728-7289ff5c-330d-11e8-9cc1-cf0cbcb606bc.jpg","api":{"public":"https://api.coinnest.co.kr/api","private":"https://api.coinnest.co.kr/api","web":"https://www.coinnest.co.kr"},"www":"https://www.coinnest.co.kr","doc":"https://www.coinnest.co.kr/doc/intro.html","fees":["https://coinnesthelp.zendesk.com/hc/ko/articles/115002110252-%EA%B1%B0%EB%9E%98-%EC%88%98%EC%88%98%EB%A3%8C%EB%8A%94-%EC%96%BC%EB%A7%88%EC%9D%B8%EA%B0%80%EC%9A%94-","https://coinnesthelp.zendesk.com/hc/ko/articles/115002110272-%EB%B9%84%ED%8A%B8%EC%BD%94%EC%9D%B8-%EC%88%98%EC%88%98%EB%A3%8C%EB%A5%BC-%EC%84%A0%ED%83%9D%ED%95%98%EB%8A%94-%EC%9D%B4%EC%9C%A0%EA%B0%80-%EB%AC%B4%EC%97%87%EC%9D%B8%EA%B0%80%EC%9A%94-"]}}},"markets":{"statusCode":200,"response":[{"id":"btc/krw","symbol":"BTC/KRW","base":"BTC","quote":"KRW","limits":{"amount":{},"price":{},"cost":{}},"precision":{}},{"id":"bch/krw","symbol":"BCH/KRW","base":"BCH","quote":"KRW","limits":{"amount":{},"price":{},"cost":{}},"precision":{}},{"id":"btg/krw","symbol":"BTG/KRW","base":"BTG","quote":"KRW","limits":{"amount":{},"price":{},"cost":{}},"precision":{}},{"id":"bcd/krw","symbol":"BCD/KRW","base":"BCD","quote":"KRW","limits":{"amount":{},"price":{},"cost":{}},"precision":{}},{"id":"ubtc/krw","symbol":"UBTC/KRW","base":"UBTC","quote":"KRW","limits":{"amount":{},"price":{},"cost":{}},"precision":{}},{"id":"btn/krw","symbol":"BTN/KRW","base":"BTN","quote":"KRW","limits":{"amount":{},"price":{},"cost":{}},"precision":{}},{"id":"kst/krw","symbol":"KST/KRW","base":"KST","quote":"KRW","limits":{"amount":{},"price":{},"cost":{}},"precision":{}},{"id":"ltc/krw","symbol":"LTC/KRW","base":"LTC","quote":"KRW","limits":{"amount":{},"price":{},"cost":{}},"precision":{}},{"id":"act/krw","symbol":"ACT/KRW","base":"ACT","quote":"KRW","limits":{"amount":{},"price":{},"cost":{}},"precision":{}},{"id":"eth/krw","symbol":"ETH/KRW","base":"ETH","quote":"KRW","limits":{"amount":{},"price":{},"cost":{}},"precision":{}},{"id":"etc/krw","symbol":"ETC/KRW","base":"ETC","quote":"KRW","limits":{"amount":{},"price":{},"cost":{}},"precision":{}},{"id":"ada/krw","symbol":"ADA/KRW","base":"ADA","quote":"KRW","limits":{"amount":{},"price":{},"cost":{}},"precision":{}},{"id":"qtum/krw","symbol":"QTUM/KRW","base":"QTUM","quote":"KRW","limits":{"amount":{},"price":{},"cost":{}},"precision":{}},{"id":"xlm/krw","symbol":"XLM/KRW","base":"XLM","quote":"KRW","limits":{"amount":{},"price":{},"cost":{}},"precision":{}},{"id":"neo/krw","symbol":"NEO/KRW","base":"NEO","quote":"KRW","limits":{"amount":{},"price":{},"cost":{}},"precision":{}},{"id":"gas/krw","symbol":"GAS/KRW","base":"GAS","quote":"KRW","limits":{"amount":{},"price":{},"cost":{}},"precision":{}},{"id":"rpx/krw","symbol":"RPX/KRW","base":"RPX","quote":"KRW","limits":{"amount":{},"price":{},"cost":{}},"precision":{}},{"id":"hsr/krw","symbol":"HSR/KRW","base":"HSR","quote":"KRW","limits":{"amount":{},"price":{},"cost":{}},"precision":{}},{"id":"knc/krw","symbol":"KNC/KRW","base":"KNC","quote":"KRW","limits":{"amount":{},"price":{},"cost":{}},"precision":{}},{"id":"tsl/krw","symbol":"TSL/KRW","base":"TSL","quote":"KRW","limits":{"amount":{},"price":{},"cost":{}},"precision":{}},{"id":"tron/krw","symbol":"TRON/KRW","base":"TRON","quote":"KRW","limits":{"amount":{},"price":{},"cost":{}},"precision":{}},{"id":"omg/krw","symbol":"OMG/KRW","base":"OMG","quote":"KRW","limits":{"amount":{},"price":{},"cost":{}},"precision":{}},{"id":"wtc/krw","symbol":"WTC/KRW","base":"WTC","quote":"KRW","limits":{"amount":{},"price":{},"cost":{}},"precision":{}},{"id":"mco/krw","symbol":"MCO/KRW","base":"MCO","quote":"KRW","limits":{"amount":{},"price":{},"cost":{}},"precision":{}},{"id":"storm/krw","symbol":"STORM/KRW","base":"STORM","quote":"KRW","limits":{"amount":{},"price":{},"cost":{}},"precision":{}},{"id":"gto/krw","symbol":"GTO/KRW","base":"GTO","quote":"KRW","limits":{"amount":{},"price":{},"cost":{}},"precision":{}},{"id":"pxs/krw","symbol":"PXS/KRW","base":"PXS","quote":"KRW","limits":{"amount":{},"price":{},"cost":{}},"precision":{}},{"id":"chat/krw","symbol":"CHAT/KRW","base":"CHAT","quote":"KRW","limits":{"amount":{},"price":{},"cost":{}},"precision":{}},{"id":"ink/krw","symbol":"INK/KRW","base":"INK","quote":"KRW","limits":{"amount":{},"price":{},"cost":{}},"precision":{}},{"id":"oc/krw","symbol":"OC/KRW","base":"OC","quote":"KRW","limits":{"amount":{},"price":{},"cost":{}},"precision":{}},{"id":"hlc/krw","symbol":"HLC/KRW","base":"HLC","quote":"KRW","limits":{"amount":{},"price":{},"cost":{}},"precision":{}},{"id":"ent/krw","symbol":"ENT/KRW","base":"ENT","quote":"KRW","limits":{"amount":{},"price":{},"cost":{}},"precision":{}},{"id":"qbt/krw","symbol":"QBT/KRW","base":"QBT","quote":"KRW","limits":{"amount":{},"price":{},"cost":{}},"precision":{}},{"id":"spc/krw","symbol":"SPC/KRW","base":"SPC","quote":"KRW","limits":{"amount":{},"price":{},"cost":{}},"precision":{}},{"id":"put/krw","symbol":"PUT/KRW","base":"PUT","quote":"KRW","limits":{"amount":{},"price":{},"cost":{}},"precision":{}}]},"ticker":{"statusCode":200,"response":{"symbol":"BTC/KRW","timestamp":1556697099000,"datetime":"2019-05-01T07:51:39.000Z","high":0,"low":0,"bid":0,"ask":0,"close":1300000,"last":1300000,"baseVolume":0,"info":{"high":0,"low":0,"buy":0,"sell":0,"last":1300000,"vol":0,"time":1556697099}}},"tickers":{"statusCode":501,"response":""},"orderBook":{"statusCode":200,"response":{"bids":[],"asks":[]}},"trades":{"statusCode":200,"response":[{"id":"721268","info":{"date":"1556332309","price":480000,"amount":0.2207,"tid":"721268","type":"buy"},"timestamp":1556332309000,"datetime":"2019-04-27T02:31:49.000Z","symbol":"BTC/KRW","side":"buy","price":480000,"amount":0.2207},{"id":"721269","info":{"date":"1556332309","price":481000,"amount":0.0972,"tid":"721269","type":"buy"},"timestamp":1556332309000,"datetime":"2019-04-27T02:31:49.000Z","symbol":"BTC/KRW","side":"buy","price":481000,"amount":0.0972},{"id":"721271","info":{"date":"1556332309","price":485000,"amount":0.1101,"tid":"721271","type":"buy"},"timestamp":1556332309000,"datetime":"2019-04-27T02:31:49.000Z","symbol":"BTC/KRW","side":"buy","price":485000,"amount":0.1101},{"id":"721270","info":{"date":"1556332309","price":481000,"amount":0.02,"tid":"721270","type":"buy"},"timestamp":1556332309000,"datetime":"2019-04-27T02:31:49.000Z","symbol":"BTC/KRW","side":"buy","price":481000,"amount":0.02},{"id":"721272","info":{"date":"1556335585","price":428000,"amount":0.0753,"tid":"721272","type":"sell"},"timestamp":1556335585000,"datetime":"2019-04-27T03:26:25.000Z","symbol":"BTC/KRW","side":"sell","price":428000,"amount":0.0753},{"id":"721273","info":{"date":"1556335609","price":428000,"amount":0.0664,"tid":"721273","type":"buy"},"timestamp":1556335609000,"datetime":"2019-04-27T03:26:49.000Z","symbol":"BTC/KRW","side":"buy","price":428000,"amount":0.0664},{"id":"721274","info":{"date":"1556335620","price":428000,"amount":0.1073,"tid":"721274","type":"buy"},"timestamp":1556335620000,"datetime":"2019-04-27T03:27:00.000Z","symbol":"BTC/KRW","side":"buy","price":428000,"amount":0.1073},{"id":"721275","info":{"date":"1556335620","price":428000,"amount":0.0753,"tid":"721275","type":"buy"},"timestamp":1556335620000,"datetime":"2019-04-27T03:27:00.000Z","symbol":"BTC/KRW","side":"buy","price":428000,"amount":0.0753},{"id":"721277","info":{"date":"1556336643","price":600000,"amount":0.0045,"tid":"721277","type":"buy"},"timestamp":1556336643000,"datetime":"2019-04-27T03:44:03.000Z","symbol":"BTC/KRW","side":"buy","price":600000,"amount":0.0045},{"id":"721276","info":{"date":"1556336643","price":600000,"amount":0.0314,"tid":"721276","type":"buy"},"timestamp":1556336643000,"datetime":"2019-04-27T03:44:03.000Z","symbol":"BTC/KRW","side":"buy","price":600000,"amount":0.0314},{"id":"721278","info":{"date":"1556337991","price":598000,"amount":0.0042,"tid":"721278","type":"buy"},"timestamp":1556337991000,"datetime":"2019-04-27T04:06:31.000Z","symbol":"BTC/KRW","side":"buy","price":598000,"amount":0.0042},{"id":"721280","info":{"date":"1556340614","price":598000,"amount":0.0025,"tid":"721280","type":"buy"},"timestamp":1556340614000,"datetime":"2019-04-27T04:50:14.000Z","symbol":"BTC/KRW","side":"buy","price":598000,"amount":0.0025},{"id":"721279","info":{"date":"1556340614","price":597000,"amount":0.003,"tid":"721279","type":"buy"},"timestamp":1556340614000,"datetime":"2019-04-27T04:50:14.000Z","symbol":"BTC/KRW","side":"buy","price":597000,"amount":0.003},{"id":"721281","info":{"date":"1556344032","price":430000,"amount":0.0467,"tid":"721281","type":"sell"},"timestamp":1556344032000,"datetime":"2019-04-27T05:47:12.000Z","symbol":"BTC/KRW","side":"sell","price":430000,"amount":0.0467},{"id":"721282","info":{"date":"1556344948","price":563000,"amount":0.023,"tid":"721282","type":"buy"},"timestamp":1556344948000,"datetime":"2019-04-27T06:02:28.000Z","symbol":"BTC/KRW","side":"buy","price":563000,"amount":0.023},{"id":"721283","info":{"date":"1556345113","price":563000,"amount":0.0013,"tid":"721283","type":"buy"},"timestamp":1556345113000,"datetime":"2019-04-27T06:05:13.000Z","symbol":"BTC/KRW","side":"buy","price":563000,"amount":0.0013},{"id":"721284","info":{"date":"1556347183","price":430000,"amount":0.0004,"tid":"721284","type":"sell"},"timestamp":1556347183000,"datetime":"2019-04-27T06:39:43.000Z","symbol":"BTC/KRW","side":"sell","price":430000,"amount":0.0004},{"id":"721285","info":{"date":"1556347505","price":548000,"amount":0.0227,"tid":"721285","type":"buy"},"timestamp":1556347505000,"datetime":"2019-04-27T06:45:05.000Z","symbol":"BTC/KRW","side":"buy","price":548000,"amount":0.0227},{"id":"721286","info":{"date":"1556347591","price":549000,"amount":0.0693,"tid":"721286","type":"sell"},"timestamp":1556347591000,"datetime":"2019-04-27T06:46:31.000Z","symbol":"BTC/KRW","side":"sell","price":549000,"amount":0.0693},{"id":"721287","info":{"date":"1556347599","price":548000,"amount":0.0027,"tid":"721287","type":"sell"},"timestamp":1556347599000,"datetime":"2019-04-27T06:46:39.000Z","symbol":"BTC/KRW","side":"sell","price":548000,"amount":0.0027},{"id":"721288","info":{"date":"1556351163","price":429000,"amount":0.0007,"tid":"721288","type":"sell"},"timestamp":1556351163000,"datetime":"2019-04-27T07:46:03.000Z","symbol":"BTC/KRW","side":"sell","price":429000,"amount":0.0007},{"id":"721289","info":{"date":"1556355769","price":427000,"amount":0.0003,"tid":"721289","type":"sell"},"timestamp":1556355769000,"datetime":"2019-04-27T09:02:49.000Z","symbol":"BTC/KRW","side":"sell","price":427000,"amount":0.0003},{"id":"721290","info":{"date":"1556356127","price":384000,"amount":0.0293,"tid":"721290","type":"buy"},"timestamp":1556356127000,"datetime":"2019-04-27T09:08:47.000Z","symbol":"BTC/KRW","side":"buy","price":384000,"amount":0.0293},{"id":"721291","info":{"date":"1556356129","price":384000,"amount":0.0352,"tid":"721291","type":"buy"},"timestamp":1556356129000,"datetime":"2019-04-27T09:08:49.000Z","symbol":"BTC/KRW","side":"buy","price":384000,"amount":0.0352},{"id":"721292","info":{"date":"1556357005","price":384000,"amount":0.0027,"tid":"721292","type":"buy"},"timestamp":1556357005000,"datetime":"2019-04-27T09:23:25.000Z","symbol":"BTC/KRW","side":"buy","price":384000,"amount":0.0027},{"id":"721293","info":{"date":"1556357006","price":384000,"amount":0.0048,"tid":"721293","type":"sell"},"timestamp":1556357006000,"datetime":"2019-04-27T09:23:26.000Z","symbol":"BTC/KRW","side":"sell","price":384000,"amount":0.0048},{"id":"721294","info":{"date":"1556364905","price":474000,"amount":0.0023,"tid":"721294","type":"buy"},"timestamp":1556364905000,"datetime":"2019-04-27T11:35:05.000Z","symbol":"BTC/KRW","side":"buy","price":474000,"amount":0.0023},{"id":"721295","info":{"date":"1556366282","price":474000,"amount":0.052,"tid":"721295","type":"buy"},"timestamp":1556366282000,"datetime":"2019-04-27T11:58:02.000Z","symbol":"BTC/KRW","side":"buy","price":474000,"amount":0.052},{"id":"721296","info":{"date":"1556367103","price":474000,"amount":0.0086,"tid":"721296","type":"buy"},"timestamp":1556367103000,"datetime":"2019-04-27T12:11:43.000Z","symbol":"BTC/KRW","side":"buy","price":474000,"amount":0.0086},{"id":"721297","info":{"date":"1556375144","price":391000,"amount":0.068,"tid":"721297","type":"sell"},"timestamp":1556375144000,"datetime":"2019-04-27T14:25:44.000Z","symbol":"BTC/KRW","side":"sell","price":391000,"amount":0.068},{"id":"721298","info":{"date":"1556375144","price":390000,"amount":0.0068,"tid":"721298","type":"sell"},"timestamp":1556375144000,"datetime":"2019-04-27T14:25:44.000Z","symbol":"BTC/KRW","side":"sell","price":390000,"amount":0.0068},{"id":"721299","info":{"date":"1556375784","price":473000,"amount":0.0548,"tid":"721299","type":"buy"},"timestamp":1556375784000,"datetime":"2019-04-27T14:36:24.000Z","symbol":"BTC/KRW","side":"buy","price":473000,"amount":0.0548},{"id":"721300","info":{"date":"1556386190","price":473000,"amount":0.0131,"tid":"721300","type":"buy"},"timestamp":1556386190000,"datetime":"2019-04-27T17:29:50.000Z","symbol":"BTC/KRW","side":"buy","price":473000,"amount":0.0131},{"id":"721301","info":{"date":"1556409604","price":478000,"amount":0.0003,"tid":"721301","type":"buy"},"timestamp":1556409604000,"datetime":"2019-04-28T00:00:04.000Z","symbol":"BTC/KRW","side":"buy","price":478000,"amount":0.0003},{"id":"721302","info":{"date":"1556412550","price":487000,"amount":0.1,"tid":"721302","type":"buy"},"timestamp":1556412550000,"datetime":"2019-04-28T00:49:10.000Z","symbol":"BTC/KRW","side":"buy","price":487000,"amount":0.1},{"id":"721303","info":{"date":"1556412584","price":488000,"amount":0.0208,"tid":"721303","type":"buy"},"timestamp":1556412584000,"datetime":"2019-04-28T00:49:44.000Z","symbol":"BTC/KRW","side":"buy","price":488000,"amount":0.0208},{"id":"721305","info":{"date":"1556416339","price":483000,"amount":0.0095,"tid":"721305","type":"buy"},"timestamp":1556416339000,"datetime":"2019-04-28T01:52:19.000Z","symbol":"BTC/KRW","side":"buy","price":483000,"amount":0.0095},{"id":"721306","info":{"date":"1556416339","price":483000,"amount":0.2275,"tid":"721306","type":"buy"},"timestamp":1556416339000,"datetime":"2019-04-28T01:52:19.000Z","symbol":"BTC/KRW","side":"buy","price":483000,"amount":0.2275},{"id":"721304","info":{"date":"1556416339","price":482000,"amount":0.0003,"tid":"721304","type":"buy"},"timestamp":1556416339000,"datetime":"2019-04-28T01:52:19.000Z","symbol":"BTC/KRW","side":"buy","price":482000,"amount":0.0003},{"id":"721308","info":{"date":"1556416518","price":483000,"amount":0.0961,"tid":"721308","type":"sell"},"timestamp":1556416518000,"datetime":"2019-04-28T01:55:18.000Z","symbol":"BTC/KRW","side":"sell","price":483000,"amount":0.0961},{"id":"721307","info":{"date":"1556416518","price":484000,"amount":0.0662,"tid":"721307","type":"sell"},"timestamp":1556416518000,"datetime":"2019-04-28T01:55:18.000Z","symbol":"BTC/KRW","side":"sell","price":484000,"amount":0.0662},{"id":"721309","info":{"date":"1556423464","price":401000,"amount":0.0043,"tid":"721309","type":"sell"},"timestamp":1556423464000,"datetime":"2019-04-28T03:51:04.000Z","symbol":"BTC/KRW","side":"sell","price":401000,"amount":0.0043},{"id":"721310","info":{"date":"1556429428","price":407000,"amount":0.0003,"tid":"721310","type":"sell"},"timestamp":1556429428000,"datetime":"2019-04-28T05:30:28.000Z","symbol":"BTC/KRW","side":"sell","price":407000,"amount":0.0003},{"id":"721311","info":{"date":"1556432762","price":479000,"amount":0.0661,"tid":"721311","type":"buy"},"timestamp":1556432762000,"datetime":"2019-04-28T06:26:02.000Z","symbol":"BTC/KRW","side":"buy","price":479000,"amount":0.0661},{"id":"721312","info":{"date":"1556432762","price":479000,"amount":0.0042,"tid":"721312","type":"buy"},"timestamp":1556432762000,"datetime":"2019-04-28T06:26:02.000Z","symbol":"BTC/KRW","side":"buy","price":479000,"amount":0.0042},{"id":"721313","info":{"date":"1556432775","price":480000,"amount":0.016,"tid":"721313","type":"buy"},"timestamp":1556432775000,"datetime":"2019-04-28T06:26:15.000Z","symbol":"BTC/KRW","side":"buy","price":480000,"amount":0.016},{"id":"721314","info":{"date":"1556439073","price":499000,"amount":0.1964,"tid":"721314","type":"buy"},"timestamp":1556439073000,"datetime":"2019-04-28T08:11:13.000Z","symbol":"BTC/KRW","side":"buy","price":499000,"amount":0.1964},{"id":"721315","info":{"date":"1556449652","price":484000,"amount":0.0383,"tid":"721315","type":"buy"},"timestamp":1556449652000,"datetime":"2019-04-28T11:07:32.000Z","symbol":"BTC/KRW","side":"buy","price":484000,"amount":0.0383},{"id":"721316","info":{"date":"1556456983","price":461000,"amount":0.0687,"tid":"721316","type":"sell"},"timestamp":1556456983000,"datetime":"2019-04-28T13:09:43.000Z","symbol":"BTC/KRW","side":"sell","price":461000,"amount":0.0687},{"id":"721317","info":{"date":"1556456983","price":460000,"amount":0.1742,"tid":"721317","type":"sell"},"timestamp":1556456983000,"datetime":"2019-04-28T13:09:43.000Z","symbol":"BTC/KRW","side":"sell","price":460000,"amount":0.1742},{"id":"721318","info":{"date":"1556457217","price":460000,"amount":0.0568,"tid":"721318","type":"sell"},"timestamp":1556457217000,"datetime":"2019-04-28T13:13:37.000Z","symbol":"BTC/KRW","side":"sell","price":460000,"amount":0.0568},{"id":"721319","info":{"date":"1556462117","price":475000,"amount":0.0687,"tid":"721319","type":"buy"},"timestamp":1556462117000,"datetime":"2019-04-28T14:35:17.000Z","symbol":"BTC/KRW","side":"buy","price":475000,"amount":0.0687},{"id":"721320","info":{"date":"1556462126","price":476000,"amount":0.16,"tid":"721320","type":"buy"},"timestamp":1556462126000,"datetime":"2019-04-28T14:35:26.000Z","symbol":"BTC/KRW","side":"buy","price":476000,"amount":0.16},{"id":"721321","info":{"date":"1556463659","price":498000,"amount":0.35,"tid":"721321","type":"buy"},"timestamp":1556463659000,"datetime":"2019-04-28T15:00:59.000Z","symbol":"BTC/KRW","side":"buy","price":498000,"amount":0.35},{"id":"721322","info":{"date":"1556469287","price":989000,"amount":0.0164,"tid":"721322","type":"buy"},"timestamp":1556469287000,"datetime":"2019-04-28T16:34:47.000Z","symbol":"BTC/KRW","side":"buy","price":989000,"amount":0.0164},{"id":"721323","info":{"date":"1556486112","price":434000,"amount":0.0006,"tid":"721323","type":"sell"},"timestamp":1556486112000,"datetime":"2019-04-28T21:15:12.000Z","symbol":"BTC/KRW","side":"sell","price":434000,"amount":0.0006},{"id":"721324","info":{"date":"1556487551","price":451000,"amount":0.0078,"tid":"721324","type":"sell"},"timestamp":1556487551000,"datetime":"2019-04-28T21:39:11.000Z","symbol":"BTC/KRW","side":"sell","price":451000,"amount":0.0078},{"id":"721325","info":{"date":"1556495544","price":500000,"amount":0.0159,"tid":"721325","type":"buy"},"timestamp":1556495544000,"datetime":"2019-04-28T23:52:24.000Z","symbol":"BTC/KRW","side":"buy","price":500000,"amount":0.0159},{"id":"721326","info":{"date":"1556497114","price":451000,"amount":0.0639,"tid":"721326","type":"sell"},"timestamp":1556497114000,"datetime":"2019-04-29T00:18:34.000Z","symbol":"BTC/KRW","side":"sell","price":451000,"amount":0.0639},{"id":"721327","info":{"date":"1556497114","price":451000,"amount":0.0655,"tid":"721327","type":"sell"},"timestamp":1556497114000,"datetime":"2019-04-29T00:18:34.000Z","symbol":"BTC/KRW","side":"sell","price":451000,"amount":0.0655},{"id":"721328","info":{"date":"1556497129","price":450000,"amount":0.0047,"tid":"721328","type":"sell"},"timestamp":1556497129000,"datetime":"2019-04-29T00:18:49.000Z","symbol":"BTC/KRW","side":"sell","price":450000,"amount":0.0047},{"id":"721329","info":{"date":"1556498729","price":499000,"amount":0.0083,"tid":"721329","type":"buy"},"timestamp":1556498729000,"datetime":"2019-04-29T00:45:29.000Z","symbol":"BTC/KRW","side":"buy","price":499000,"amount":0.0083},{"id":"721330","info":{"date":"1556498729","price":499000,"amount":0.1468,"tid":"721330","type":"buy"},"timestamp":1556498729000,"datetime":"2019-04-29T00:45:29.000Z","symbol":"BTC/KRW","side":"buy","price":499000,"amount":0.1468},{"id":"721331","info":{"date":"1556498730","price":499000,"amount":0.0639,"tid":"721331","type":"sell"},"timestamp":1556498730000,"datetime":"2019-04-29T00:45:30.000Z","symbol":"BTC/KRW","side":"sell","price":499000,"amount":0.0639},{"id":"721332","info":{"date":"1556498785","price":500000,"amount":0.0023,"tid":"721332","type":"buy"},"timestamp":1556498785000,"datetime":"2019-04-29T00:46:25.000Z","symbol":"BTC/KRW","side":"buy","price":500000,"amount":0.0023},{"id":"721333","info":{"date":"1556500418","price":501000,"amount":0.0718,"tid":"721333","type":"sell"},"timestamp":1556500418000,"datetime":"2019-04-29T01:13:38.000Z","symbol":"BTC/KRW","side":"sell","price":501000,"amount":0.0718},{"id":"721334","info":{"date":"1556501451","price":501000,"amount":0.0565,"tid":"721334","type":"buy"},"timestamp":1556501451000,"datetime":"2019-04-29T01:30:51.000Z","symbol":"BTC/KRW","side":"buy","price":501000,"amount":0.0565},{"id":"721335","info":{"date":"1556501827","price":501000,"amount":0.0334,"tid":"721335","type":"buy"},"timestamp":1556501827000,"datetime":"2019-04-29T01:37:07.000Z","symbol":"BTC/KRW","side":"buy","price":501000,"amount":0.0334},{"id":"721336","info":{"date":"1556503052","price":500000,"amount":0.0084,"tid":"721336","type":"sell"},"timestamp":1556503052000,"datetime":"2019-04-29T01:57:32.000Z","symbol":"BTC/KRW","side":"sell","price":500000,"amount":0.0084},{"id":"721337","info":{"date":"1556503587","price":501000,"amount":0.029,"tid":"721337","type":"buy"},"timestamp":1556503587000,"datetime":"2019-04-29T02:06:27.000Z","symbol":"BTC/KRW","side":"buy","price":501000,"amount":0.029},{"id":"721338","info":{"date":"1556505364","price":501000,"amount":0.0166,"tid":"721338","type":"buy"},"timestamp":1556505364000,"datetime":"2019-04-29T02:36:04.000Z","symbol":"BTC/KRW","side":"buy","price":501000,"amount":0.0166},{"id":"721339","info":{"date":"1556506232","price":799000,"amount":0.0516,"tid":"721339","type":"buy"},"timestamp":1556506232000,"datetime":"2019-04-29T02:50:32.000Z","symbol":"BTC/KRW","side":"buy","price":799000,"amount":0.0516},{"id":"721340","info":{"date":"1556507376","price":797000,"amount":0.0201,"tid":"721340","type":"buy"},"timestamp":1556507376000,"datetime":"2019-04-29T03:09:36.000Z","symbol":"BTC/KRW","side":"buy","price":797000,"amount":0.0201},{"id":"721341","info":{"date":"1556507902","price":797000,"amount":0.1547,"tid":"721341","type":"sell"},"timestamp":1556507902000,"datetime":"2019-04-29T03:18:22.000Z","symbol":"BTC/KRW","side":"sell","price":797000,"amount":0.1547},{"id":"721342","info":{"date":"1556508575","price":501000,"amount":0.0067,"tid":"721342","type":"sell"},"timestamp":1556508575000,"datetime":"2019-04-29T03:29:35.000Z","symbol":"BTC/KRW","side":"sell","price":501000,"amount":0.0067},{"id":"721343","info":{"date":"1556512548","price":749000,"amount":0.0067,"tid":"721343","type":"buy"},"timestamp":1556512548000,"datetime":"2019-04-29T04:35:48.000Z","symbol":"BTC/KRW","side":"buy","price":749000,"amount":0.0067},{"id":"721344","info":{"date":"1556512774","price":749000,"amount":0.1952,"tid":"721344","type":"sell"},"timestamp":1556512774000,"datetime":"2019-04-29T04:39:34.000Z","symbol":"BTC/KRW","side":"sell","price":749000,"amount":0.1952},{"id":"721345","info":{"date":"1556512865","price":750000,"amount":0.0334,"tid":"721345","type":"buy"},"timestamp":1556512865000,"datetime":"2019-04-29T04:41:05.000Z","symbol":"BTC/KRW","side":"buy","price":750000,"amount":0.0334},{"id":"721346","info":{"date":"1556512873","price":751000,"amount":0.0583,"tid":"721346","type":"sell"},"timestamp":1556512873000,"datetime":"2019-04-29T04:41:13.000Z","symbol":"BTC/KRW","side":"sell","price":751000,"amount":0.0583},{"id":"721347","info":{"date":"1556513033","price":776000,"amount":0.0039,"tid":"721347","type":"buy"},"timestamp":1556513033000,"datetime":"2019-04-29T04:43:53.000Z","symbol":"BTC/KRW","side":"buy","price":776000,"amount":0.0039},{"id":"721348","info":{"date":"1556513654","price":751000,"amount":0.0041,"tid":"721348","type":"sell"},"timestamp":1556513654000,"datetime":"2019-04-29T04:54:14.000Z","symbol":"BTC/KRW","side":"sell","price":751000,"amount":0.0041},{"id":"721349","info":{"date":"1556515538","price":751000,"amount":0.0041,"tid":"721349","type":"sell"},"timestamp":1556515538000,"datetime":"2019-04-29T05:25:38.000Z","symbol":"BTC/KRW","side":"sell","price":751000,"amount":0.0041},{"id":"721350","info":{"date":"1556515538","price":750000,"amount":0.0153,"tid":"721350","type":"sell"},"timestamp":1556515538000,"datetime":"2019-04-29T05:25:38.000Z","symbol":"BTC/KRW","side":"sell","price":750000,"amount":0.0153},{"id":"721351","info":{"date":"1556516165","price":674000,"amount":0.0625,"tid":"721351","type":"buy"},"timestamp":1556516165000,"datetime":"2019-04-29T05:36:05.000Z","symbol":"BTC/KRW","side":"buy","price":674000,"amount":0.0625},{"id":"721352","info":{"date":"1556516181","price":675000,"amount":0.2571,"tid":"721352","type":"buy"},"timestamp":1556516181000,"datetime":"2019-04-29T05:36:21.000Z","symbol":"BTC/KRW","side":"buy","price":675000,"amount":0.2571},{"id":"721353","info":{"date":"1556523252","price":675000,"amount":0.0007,"tid":"721353","type":"buy"},"timestamp":1556523252000,"datetime":"2019-04-29T07:34:12.000Z","symbol":"BTC/KRW","side":"buy","price":675000,"amount":0.0007},{"id":"721354","info":{"date":"1556523571","price":503000,"amount":0.0007,"tid":"721354","type":"sell"},"timestamp":1556523571000,"datetime":"2019-04-29T07:39:31.000Z","symbol":"BTC/KRW","side":"sell","price":503000,"amount":0.0007},{"id":"721355","info":{"date":"1556528550","price":667000,"amount":0.0163,"tid":"721355","type":"buy"},"timestamp":1556528550000,"datetime":"2019-04-29T09:02:30.000Z","symbol":"BTC/KRW","side":"buy","price":667000,"amount":0.0163},{"id":"721356","info":{"date":"1556533933","price":507000,"amount":0.0986,"tid":"721356","type":"sell"},"timestamp":1556533933000,"datetime":"2019-04-29T10:32:13.000Z","symbol":"BTC/KRW","side":"sell","price":507000,"amount":0.0986},{"id":"721358","info":{"date":"1556533933","price":504000,"amount":0.011,"tid":"721358","type":"sell"},"timestamp":1556533933000,"datetime":"2019-04-29T10:32:13.000Z","symbol":"BTC/KRW","side":"sell","price":504000,"amount":0.011},{"id":"721357","info":{"date":"1556533933","price":506000,"amount":0.0904,"tid":"721357","type":"sell"},"timestamp":1556533933000,"datetime":"2019-04-29T10:32:13.000Z","symbol":"BTC/KRW","side":"sell","price":506000,"amount":0.0904},{"id":"721359","info":{"date":"1556534664","price":505000,"amount":0.0073,"tid":"721359","type":"sell"},"timestamp":1556534664000,"datetime":"2019-04-29T10:44:24.000Z","symbol":"BTC/KRW","side":"sell","price":505000,"amount":0.0073},{"id":"721360","info":{"date":"1556534664","price":504000,"amount":0.1771,"tid":"721360","type":"sell"},"timestamp":1556534664000,"datetime":"2019-04-29T10:44:24.000Z","symbol":"BTC/KRW","side":"sell","price":504000,"amount":0.1771},{"id":"721361","info":{"date":"1556535250","price":501000,"amount":0.0474,"tid":"721361","type":"buy"},"timestamp":1556535250000,"datetime":"2019-04-29T10:54:10.000Z","symbol":"BTC/KRW","side":"buy","price":501000,"amount":0.0474},{"id":"721362","info":{"date":"1556535844","price":501000,"amount":0.0591,"tid":"721362","type":"buy"},"timestamp":1556535844000,"datetime":"2019-04-29T11:04:04.000Z","symbol":"BTC/KRW","side":"buy","price":501000,"amount":0.0591},{"id":"721363","info":{"date":"1556537341","price":624000,"amount":0.0801,"tid":"721363","type":"sell"},"timestamp":1556537341000,"datetime":"2019-04-29T11:29:01.000Z","symbol":"BTC/KRW","side":"sell","price":624000,"amount":0.0801},{"id":"721364","info":{"date":"1556537369","price":624000,"amount":0.0053,"tid":"721364","type":"sell"},"timestamp":1556537369000,"datetime":"2019-04-29T11:29:29.000Z","symbol":"BTC/KRW","side":"sell","price":624000,"amount":0.0053},{"id":"721365","info":{"date":"1556537547","price":524000,"amount":0.0853,"tid":"721365","type":"buy"},"timestamp":1556537547000,"datetime":"2019-04-29T11:32:27.000Z","symbol":"BTC/KRW","side":"buy","price":524000,"amount":0.0853},{"id":"721366","info":{"date":"1556537680","price":634000,"amount":0.01,"tid":"721366","type":"sell"},"timestamp":1556537680000,"datetime":"2019-04-29T11:34:40.000Z","symbol":"BTC/KRW","side":"sell","price":634000,"amount":0.01},{"id":"721367","info":{"date":"1556537776","price":631000,"amount":0.0708,"tid":"721367","type":"sell"},"timestamp":1556537776000,"datetime":"2019-04-29T11:36:16.000Z","symbol":"BTC/KRW","side":"sell","price":631000,"amount":0.0708},{"id":"721368","info":{"date":"1556537850","price":504000,"amount":0.038,"tid":"721368","type":"buy"},"timestamp":1556537850000,"datetime":"2019-04-29T11:37:30.000Z","symbol":"BTC/KRW","side":"buy","price":504000,"amount":0.038},{"id":"721369","info":{"date":"1556537862","price":504000,"amount":0.0328,"tid":"721369","type":"buy"},"timestamp":1556537862000,"datetime":"2019-04-29T11:37:42.000Z","symbol":"BTC/KRW","side":"buy","price":504000,"amount":0.0328},{"id":"721370","info":{"date":"1556537943","price":624000,"amount":0.01,"tid":"721370","type":"buy"},"timestamp":1556537943000,"datetime":"2019-04-29T11:39:03.000Z","symbol":"BTC/KRW","side":"buy","price":624000,"amount":0.01},{"id":"721371","info":{"date":"1556538056","price":621000,"amount":0.0574,"tid":"721371","type":"sell"},"timestamp":1556538056000,"datetime":"2019-04-29T11:40:56.000Z","symbol":"BTC/KRW","side":"sell","price":621000,"amount":0.0574},{"id":"721372","info":{"date":"1556538062","price":620000,"amount":0.002,"tid":"721372","type":"sell"},"timestamp":1556538062000,"datetime":"2019-04-29T11:41:02.000Z","symbol":"BTC/KRW","side":"sell","price":620000,"amount":0.002},{"id":"721373","info":{"date":"1556538075","price":620000,"amount":0.008,"tid":"721373","type":"sell"},"timestamp":1556538075000,"datetime":"2019-04-29T11:41:15.000Z","symbol":"BTC/KRW","side":"sell","price":620000,"amount":0.008},{"id":"721374","info":{"date":"1556538225","price":509000,"amount":0.0573,"tid":"721374","type":"buy"},"timestamp":1556538225000,"datetime":"2019-04-29T11:43:45.000Z","symbol":"BTC/KRW","side":"buy","price":509000,"amount":0.0573},{"id":"721375","info":{"date":"1556538935","price":600000,"amount":0.01,"tid":"721375","type":"buy"},"timestamp":1556538935000,"datetime":"2019-04-29T11:55:35.000Z","symbol":"BTC/KRW","side":"buy","price":600000,"amount":0.01},{"id":"721376","info":{"date":"1556539057","price":617000,"amount":0.01,"tid":"721376","type":"sell"},"timestamp":1556539057000,"datetime":"2019-04-29T11:57:37.000Z","symbol":"BTC/KRW","side":"sell","price":617000,"amount":0.01},{"id":"721377","info":{"date":"1556539064","price":617000,"amount":0.0372,"tid":"721377","type":"sell"},"timestamp":1556539064000,"datetime":"2019-04-29T11:57:44.000Z","symbol":"BTC/KRW","side":"sell","price":617000,"amount":0.0372},{"id":"721378","info":{"date":"1556539073","price":616000,"amount":0.01,"tid":"721378","type":"sell"},"timestamp":1556539073000,"datetime":"2019-04-29T11:57:53.000Z","symbol":"BTC/KRW","side":"sell","price":616000,"amount":0.01},{"id":"721379","info":{"date":"1556539161","price":509000,"amount":0.0427,"tid":"721379","type":"buy"},"timestamp":1556539161000,"datetime":"2019-04-29T11:59:21.000Z","symbol":"BTC/KRW","side":"buy","price":509000,"amount":0.0427},{"id":"721380","info":{"date":"1556539179","price":509000,"amount":0.0045,"tid":"721380","type":"buy"},"timestamp":1556539179000,"datetime":"2019-04-29T11:59:39.000Z","symbol":"BTC/KRW","side":"buy","price":509000,"amount":0.0045},{"id":"721381","info":{"date":"1556539264","price":613000,"amount":0.0391,"tid":"721381","type":"sell"},"timestamp":1556539264000,"datetime":"2019-04-29T12:01:04.000Z","symbol":"BTC/KRW","side":"sell","price":613000,"amount":0.0391},{"id":"721382","info":{"date":"1556539318","price":504000,"amount":0.0242,"tid":"721382","type":"buy"},"timestamp":1556539318000,"datetime":"2019-04-29T12:01:58.000Z","symbol":"BTC/KRW","side":"buy","price":504000,"amount":0.0242},{"id":"721383","info":{"date":"1556539325","price":504000,"amount":0.0148,"tid":"721383","type":"buy"},"timestamp":1556539325000,"datetime":"2019-04-29T12:02:05.000Z","symbol":"BTC/KRW","side":"buy","price":504000,"amount":0.0148},{"id":"721384","info":{"date":"1556539571","price":600000,"amount":0.01,"tid":"721384","type":"buy"},"timestamp":1556539571000,"datetime":"2019-04-29T12:06:11.000Z","symbol":"BTC/KRW","side":"buy","price":600000,"amount":0.01},{"id":"721385","info":{"date":"1556539644","price":614000,"amount":0.01,"tid":"721385","type":"sell"},"timestamp":1556539644000,"datetime":"2019-04-29T12:07:24.000Z","symbol":"BTC/KRW","side":"sell","price":614000,"amount":0.01},{"id":"721386","info":{"date":"1556539769","price":600000,"amount":0.0221,"tid":"721386","type":"sell"},"timestamp":1556539769000,"datetime":"2019-04-29T12:09:29.000Z","symbol":"BTC/KRW","side":"sell","price":600000,"amount":0.0221},{"id":"721387","info":{"date":"1556539775","price":600000,"amount":0.0107,"tid":"721387","type":"sell"},"timestamp":1556539775000,"datetime":"2019-04-29T12:09:35.000Z","symbol":"BTC/KRW","side":"sell","price":600000,"amount":0.0107},{"id":"721388","info":{"date":"1556539843","price":508000,"amount":0.0328,"tid":"721388","type":"buy"},"timestamp":1556539843000,"datetime":"2019-04-29T12:10:43.000Z","symbol":"BTC/KRW","side":"buy","price":508000,"amount":0.0328},{"id":"721389","info":{"date":"1556539843","price":509000,"amount":0.01,"tid":"721389","type":"buy"},"timestamp":1556539843000,"datetime":"2019-04-29T12:10:43.000Z","symbol":"BTC/KRW","side":"buy","price":509000,"amount":0.01},{"id":"721390","info":{"date":"1556540123","price":599000,"amount":0.01,"tid":"721390","type":"sell"},"timestamp":1556540123000,"datetime":"2019-04-29T12:15:23.000Z","symbol":"BTC/KRW","side":"sell","price":599000,"amount":0.01},{"id":"721391","info":{"date":"1556541609","price":620000,"amount":0.0023,"tid":"721391","type":"buy"},"timestamp":1556541609000,"datetime":"2019-04-29T12:40:09.000Z","symbol":"BTC/KRW","side":"buy","price":620000,"amount":0.0023},{"id":"721392","info":{"date":"1556542979","price":502000,"amount":0.0164,"tid":"721392","type":"sell"},"timestamp":1556542979000,"datetime":"2019-04-29T13:02:59.000Z","symbol":"BTC/KRW","side":"sell","price":502000,"amount":0.0164},{"id":"721393","info":{"date":"1556543005","price":502000,"amount":0.0167,"tid":"721393","type":"sell"},"timestamp":1556543005000,"datetime":"2019-04-29T13:03:25.000Z","symbol":"BTC/KRW","side":"sell","price":502000,"amount":0.0167},{"id":"721394","info":{"date":"1556543005","price":501000,"amount":0.0133,"tid":"721394","type":"sell"},"timestamp":1556543005000,"datetime":"2019-04-29T13:03:25.000Z","symbol":"BTC/KRW","side":"sell","price":501000,"amount":0.0133},{"id":"721395","info":{"date":"1556545955","price":501000,"amount":0.0003,"tid":"721395","type":"sell"},"timestamp":1556545955000,"datetime":"2019-04-29T13:52:35.000Z","symbol":"BTC/KRW","side":"sell","price":501000,"amount":0.0003},{"id":"721396","info":{"date":"1556546009","price":599000,"amount":0.0141,"tid":"721396","type":"buy"},"timestamp":1556546009000,"datetime":"2019-04-29T13:53:29.000Z","symbol":"BTC/KRW","side":"buy","price":599000,"amount":0.0141},{"id":"721398","info":{"date":"1556546074","price":557000,"amount":0.0002,"tid":"721398","type":"sell"},"timestamp":1556546074000,"datetime":"2019-04-29T13:54:34.000Z","symbol":"BTC/KRW","side":"sell","price":557000,"amount":0.0002},{"id":"721397","info":{"date":"1556546074","price":558000,"amount":0.0151,"tid":"721397","type":"sell"},"timestamp":1556546074000,"datetime":"2019-04-29T13:54:34.000Z","symbol":"BTC/KRW","side":"sell","price":558000,"amount":0.0151},{"id":"721399","info":{"date":"1556549377","price":615000,"amount":0.034,"tid":"721399","type":"buy"},"timestamp":1556549377000,"datetime":"2019-04-29T14:49:37.000Z","symbol":"BTC/KRW","side":"buy","price":615000,"amount":0.034},{"id":"721400","info":{"date":"1556549377","price":615000,"amount":0.1726,"tid":"721400","type":"buy"},"timestamp":1556549377000,"datetime":"2019-04-29T14:49:37.000Z","symbol":"BTC/KRW","side":"buy","price":615000,"amount":0.1726},{"id":"721401","info":{"date":"1556549389","price":616000,"amount":0.2,"tid":"721401","type":"buy"},"timestamp":1556549389000,"datetime":"2019-04-29T14:49:49.000Z","symbol":"BTC/KRW","side":"buy","price":616000,"amount":0.2},{"id":"721402","info":{"date":"1556549727","price":600000,"amount":0.0404,"tid":"721402","type":"sell"},"timestamp":1556549727000,"datetime":"2019-04-29T14:55:27.000Z","symbol":"BTC/KRW","side":"sell","price":600000,"amount":0.0404},{"id":"721403","info":{"date":"1556549776","price":601000,"amount":0.0348,"tid":"721403","type":"sell"},"timestamp":1556549776000,"datetime":"2019-04-29T14:56:16.000Z","symbol":"BTC/KRW","side":"sell","price":601000,"amount":0.0348},{"id":"721404","info":{"date":"1556549776","price":600000,"amount":0.3402,"tid":"721404","type":"sell"},"timestamp":1556549776000,"datetime":"2019-04-29T14:56:16.000Z","symbol":"BTC/KRW","side":"sell","price":600000,"amount":0.3402},{"id":"721405","info":{"date":"1556550828","price":689000,"amount":0.0003,"tid":"721405","type":"buy"},"timestamp":1556550828000,"datetime":"2019-04-29T15:13:48.000Z","symbol":"BTC/KRW","side":"buy","price":689000,"amount":0.0003},{"id":"721406","info":{"date":"1556553274","price":689000,"amount":0.005,"tid":"721406","type":"buy"},"timestamp":1556553274000,"datetime":"2019-04-29T15:54:34.000Z","symbol":"BTC/KRW","side":"buy","price":689000,"amount":0.005},{"id":"721407","info":{"date":"1556557215","price":689000,"amount":0.0295,"tid":"721407","type":"buy"},"timestamp":1556557215000,"datetime":"2019-04-29T17:00:15.000Z","symbol":"BTC/KRW","side":"buy","price":689000,"amount":0.0295},{"id":"721408","info":{"date":"1556557215","price":690000,"amount":0.0016,"tid":"721408","type":"buy"},"timestamp":1556557215000,"datetime":"2019-04-29T17:00:15.000Z","symbol":"BTC/KRW","side":"buy","price":690000,"amount":0.0016},{"id":"721409","info":{"date":"1556557215","price":700000,"amount":0.0109,"tid":"721409","type":"buy"},"timestamp":1556557215000,"datetime":"2019-04-29T17:00:15.000Z","symbol":"BTC/KRW","side":"buy","price":700000,"amount":0.0109},{"id":"721410","info":{"date":"1556557215","price":979000,"amount":0.1582,"tid":"721410","type":"buy"},"timestamp":1556557215000,"datetime":"2019-04-29T17:00:15.000Z","symbol":"BTC/KRW","side":"buy","price":979000,"amount":0.1582},{"id":"721411","info":{"date":"1556557268","price":998000,"amount":0.0726,"tid":"721411","type":"buy"},"timestamp":1556557268000,"datetime":"2019-04-29T17:01:08.000Z","symbol":"BTC/KRW","side":"buy","price":998000,"amount":0.0726},{"id":"721412","info":{"date":"1556557295","price":1000000,"amount":0.0001,"tid":"721412","type":"buy"},"timestamp":1556557295000,"datetime":"2019-04-29T17:01:35.000Z","symbol":"BTC/KRW","side":"buy","price":1000000,"amount":0.0001},{"id":"721413","info":{"date":"1556557295","price":1000000,"amount":0.0001,"tid":"721413","type":"buy"},"timestamp":1556557295000,"datetime":"2019-04-29T17:01:35.000Z","symbol":"BTC/KRW","side":"buy","price":1000000,"amount":0.0001},{"id":"721414","info":{"date":"1556557295","price":1100000,"amount":0.0132,"tid":"721414","type":"buy"},"timestamp":1556557295000,"datetime":"2019-04-29T17:01:35.000Z","symbol":"BTC/KRW","side":"buy","price":1100000,"amount":0.0132},{"id":"721415","info":{"date":"1556557295","price":1490000,"amount":0.0028,"tid":"721415","type":"buy"},"timestamp":1556557295000,"datetime":"2019-04-29T17:01:35.000Z","symbol":"BTC/KRW","side":"buy","price":1490000,"amount":0.0028},{"id":"721416","info":{"date":"1556557295","price":1698000,"amount":0.0179,"tid":"721416","type":"buy"},"timestamp":1556557295000,"datetime":"2019-04-29T17:01:35.000Z","symbol":"BTC/KRW","side":"buy","price":1698000,"amount":0.0179},{"id":"721417","info":{"date":"1556557295","price":3900000,"amount":0.0029,"tid":"721417","type":"buy"},"timestamp":1556557295000,"datetime":"2019-04-29T17:01:35.000Z","symbol":"BTC/KRW","side":"buy","price":3900000,"amount":0.0029},{"id":"721418","info":{"date":"1556557295","price":3998000,"amount":0.0007,"tid":"721418","type":"buy"},"timestamp":1556557295000,"datetime":"2019-04-29T17:01:35.000Z","symbol":"BTC/KRW","side":"buy","price":3998000,"amount":0.0007},{"id":"721419","info":{"date":"1556557295","price":4722000,"amount":0.0244,"tid":"721419","type":"buy"},"timestamp":1556557295000,"datetime":"2019-04-29T17:01:35.000Z","symbol":"BTC/KRW","side":"buy","price":4722000,"amount":0.0244},{"id":"721420","info":{"date":"1556557307","price":4890000,"amount":0.0096,"tid":"721420","type":"buy"},"timestamp":1556557307000,"datetime":"2019-04-29T17:01:47.000Z","symbol":"BTC/KRW","side":"buy","price":4890000,"amount":0.0096},{"id":"721421","info":{"date":"1556557307","price":4890000,"amount":0.0035,"tid":"721421","type":"buy"},"timestamp":1556557307000,"datetime":"2019-04-29T17:01:47.000Z","symbol":"BTC/KRW","side":"buy","price":4890000,"amount":0.0035},{"id":"721422","info":{"date":"1556557307","price":4890000,"amount":0.0008,"tid":"721422","type":"buy"},"timestamp":1556557307000,"datetime":"2019-04-29T17:01:47.000Z","symbol":"BTC/KRW","side":"buy","price":4890000,"amount":0.0008},{"id":"721423","info":{"date":"1556557320","price":7450000,"amount":0.0345,"tid":"721423","type":"buy"},"timestamp":1556557320000,"datetime":"2019-04-29T17:02:00.000Z","symbol":"BTC/KRW","side":"buy","price":7450000,"amount":0.0345},{"id":"721424","info":{"date":"1556557336","price":8990000,"amount":0.0005,"tid":"721424","type":"buy"},"timestamp":1556557336000,"datetime":"2019-04-29T17:02:16.000Z","symbol":"BTC/KRW","side":"buy","price":8990000,"amount":0.0005},{"id":"721426","info":{"date":"1556557336","price":12300000,"amount":0.0041,"tid":"721426","type":"buy"},"timestamp":1556557336000,"datetime":"2019-04-29T17:02:16.000Z","symbol":"BTC/KRW","side":"buy","price":12300000,"amount":0.0041},{"id":"721427","info":{"date":"1556557336","price":12411000,"amount":0.0153,"tid":"721427","type":"buy"},"timestamp":1556557336000,"datetime":"2019-04-29T17:02:16.000Z","symbol":"BTC/KRW","side":"buy","price":12411000,"amount":0.0153},{"id":"721425","info":{"date":"1556557336","price":10000000,"amount":0.001,"tid":"721425","type":"buy"},"timestamp":1556557336000,"datetime":"2019-04-29T17:02:16.000Z","symbol":"BTC/KRW","side":"buy","price":10000000,"amount":0.001},{"id":"721428","info":{"date":"1556557344","price":12500000,"amount":0.0003,"tid":"721428","type":"buy"},"timestamp":1556557344000,"datetime":"2019-04-29T17:02:24.000Z","symbol":"BTC/KRW","side":"buy","price":12500000,"amount":0.0003},{"id":"721429","info":{"date":"1556557356","price":12500000,"amount":0.0092,"tid":"721429","type":"buy"},"timestamp":1556557356000,"datetime":"2019-04-29T17:02:36.000Z","symbol":"BTC/KRW","side":"buy","price":12500000,"amount":0.0092},{"id":"721430","info":{"date":"1556557365","price":12500000,"amount":0.001,"tid":"721430","type":"buy"},"timestamp":1556557365000,"datetime":"2019-04-29T17:02:45.000Z","symbol":"BTC/KRW","side":"buy","price":12500000,"amount":0.001},{"id":"721431","info":{"date":"1556557373","price":12500000,"amount":0.0001,"tid":"721431","type":"buy"},"timestamp":1556557373000,"datetime":"2019-04-29T17:02:53.000Z","symbol":"BTC/KRW","side":"buy","price":12500000,"amount":0.0001},{"id":"721433","info":{"date":"1556559631","price":9800000,"amount":0.001,"tid":"721433","type":"sell"},"timestamp":1556559631000,"datetime":"2019-04-29T17:40:31.000Z","symbol":"BTC/KRW","side":"sell","price":9800000,"amount":0.001},{"id":"721432","info":{"date":"1556559631","price":9801000,"amount":0.0024,"tid":"721432","type":"sell"},"timestamp":1556559631000,"datetime":"2019-04-29T17:40:31.000Z","symbol":"BTC/KRW","side":"sell","price":9801000,"amount":0.0024},{"id":"721434","info":{"date":"1556560022","price":601000,"amount":0.001,"tid":"721434","type":"buy"},"timestamp":1556560022000,"datetime":"2019-04-29T17:47:02.000Z","symbol":"BTC/KRW","side":"buy","price":601000,"amount":0.001},{"id":"721435","info":{"date":"1556560555","price":5239000,"amount":0.0182,"tid":"721435","type":"sell"},"timestamp":1556560555000,"datetime":"2019-04-29T17:55:55.000Z","symbol":"BTC/KRW","side":"sell","price":5239000,"amount":0.0182},{"id":"721436","info":{"date":"1556560779","price":530000,"amount":0.001,"tid":"721436","type":"buy"},"timestamp":1556560779000,"datetime":"2019-04-29T17:59:39.000Z","symbol":"BTC/KRW","side":"buy","price":530000,"amount":0.001},{"id":"721437","info":{"date":"1556560780","price":530000,"amount":0.0024,"tid":"721437","type":"sell"},"timestamp":1556560780000,"datetime":"2019-04-29T17:59:40.000Z","symbol":"BTC/KRW","side":"sell","price":530000,"amount":0.0024},{"id":"721438","info":{"date":"1556560845","price":5228000,"amount":0.0001,"tid":"721438","type":"sell"},"timestamp":1556560845000,"datetime":"2019-04-29T18:00:45.000Z","symbol":"BTC/KRW","side":"sell","price":5228000,"amount":0.0001},{"id":"721439","info":{"date":"1556560875","price":5230000,"amount":0.0001,"tid":"721439","type":"sell"},"timestamp":1556560875000,"datetime":"2019-04-29T18:01:15.000Z","symbol":"BTC/KRW","side":"sell","price":5230000,"amount":0.0001},{"id":"721440","info":{"date":"1556561087","price":5200000,"amount":0.0001,"tid":"721440","type":"sell"},"timestamp":1556561087000,"datetime":"2019-04-29T18:04:47.000Z","symbol":"BTC/KRW","side":"sell","price":5200000,"amount":0.0001},{"id":"721441","info":{"date":"1556565397","price":524000,"amount":0.0002,"tid":"721441","type":"sell"},"timestamp":1556565397000,"datetime":"2019-04-29T19:16:37.000Z","symbol":"BTC/KRW","side":"sell","price":524000,"amount":0.0002},{"id":"721442","info":{"date":"1556565594","price":699000,"amount":0.0004,"tid":"721442","type":"buy"},"timestamp":1556565594000,"datetime":"2019-04-29T19:19:54.000Z","symbol":"BTC/KRW","side":"buy","price":699000,"amount":0.0004},{"id":"721443","info":{"date":"1556569644","price":524000,"amount":0.003,"tid":"721443","type":"sell"},"timestamp":1556569644000,"datetime":"2019-04-29T20:27:24.000Z","symbol":"BTC/KRW","side":"sell","price":524000,"amount":0.003},{"id":"721444","info":{"date":"1556570947","price":557000,"amount":0.0003,"tid":"721444","type":"sell"},"timestamp":1556570947000,"datetime":"2019-04-29T20:49:07.000Z","symbol":"BTC/KRW","side":"sell","price":557000,"amount":0.0003},{"id":"721445","info":{"date":"1556574297","price":609000,"amount":0.0032,"tid":"721445","type":"buy"},"timestamp":1556574297000,"datetime":"2019-04-29T21:44:57.000Z","symbol":"BTC/KRW","side":"buy","price":609000,"amount":0.0032},{"id":"721446","info":{"date":"1556574297","price":610000,"amount":0.001,"tid":"721446","type":"buy"},"timestamp":1556574297000,"datetime":"2019-04-29T21:44:57.000Z","symbol":"BTC/KRW","side":"buy","price":610000,"amount":0.001},{"id":"721447","info":{"date":"1556577026","price":1983000,"amount":0.0157,"tid":"721447","type":"buy"},"timestamp":1556577026000,"datetime":"2019-04-29T22:30:26.000Z","symbol":"BTC/KRW","side":"buy","price":1983000,"amount":0.0157},{"id":"721448","info":{"date":"1556586581","price":653000,"amount":0.003,"tid":"721448","type":"sell"},"timestamp":1556586581000,"datetime":"2019-04-30T01:09:41.000Z","symbol":"BTC/KRW","side":"sell","price":653000,"amount":0.003},{"id":"721449","info":{"date":"1556586581","price":653000,"amount":0.0211,"tid":"721449","type":"sell"},"timestamp":1556586581000,"datetime":"2019-04-30T01:09:41.000Z","symbol":"BTC/KRW","side":"sell","price":653000,"amount":0.0211},{"id":"721450","info":{"date":"1556587116","price":1160000,"amount":0.0515,"tid":"721450","type":"buy"},"timestamp":1556587116000,"datetime":"2019-04-30T01:18:36.000Z","symbol":"BTC/KRW","side":"buy","price":1160000,"amount":0.0515},{"id":"721451","info":{"date":"1556587502","price":1178000,"amount":0.003,"tid":"721451","type":"buy"},"timestamp":1556587502000,"datetime":"2019-04-30T01:25:02.000Z","symbol":"BTC/KRW","side":"buy","price":1178000,"amount":0.003},{"id":"721452","info":{"date":"1556587512","price":1179000,"amount":0.0001,"tid":"721452","type":"buy"},"timestamp":1556587512000,"datetime":"2019-04-30T01:25:12.000Z","symbol":"BTC/KRW","side":"buy","price":1179000,"amount":0.0001},{"id":"721453","info":{"date":"1556587512","price":1180000,"amount":0.0041,"tid":"721453","type":"buy"},"timestamp":1556587512000,"datetime":"2019-04-30T01:25:12.000Z","symbol":"BTC/KRW","side":"buy","price":1180000,"amount":0.0041},{"id":"721454","info":{"date":"1556587536","price":1180000,"amount":0.0001,"tid":"721454","type":"buy"},"timestamp":1556587536000,"datetime":"2019-04-30T01:25:36.000Z","symbol":"BTC/KRW","side":"buy","price":1180000,"amount":0.0001},{"id":"721455","info":{"date":"1556588189","price":1866000,"amount":0.0019,"tid":"721455","type":"buy"},"timestamp":1556588189000,"datetime":"2019-04-30T01:36:29.000Z","symbol":"BTC/KRW","side":"buy","price":1866000,"amount":0.0019},{"id":"721456","info":{"date":"1556591718","price":1101000,"amount":0.0032,"tid":"721456","type":"sell"},"timestamp":1556591718000,"datetime":"2019-04-30T02:35:18.000Z","symbol":"BTC/KRW","side":"sell","price":1101000,"amount":0.0032},{"id":"721457","info":{"date":"1556591718","price":1100000,"amount":0.0226,"tid":"721457","type":"sell"},"timestamp":1556591718000,"datetime":"2019-04-30T02:35:18.000Z","symbol":"BTC/KRW","side":"sell","price":1100000,"amount":0.0226},{"id":"721458","info":{"date":"1556601811","price":1000000,"amount":0.0001,"tid":"721458","type":"buy"},"timestamp":1556601811000,"datetime":"2019-04-30T05:23:31.000Z","symbol":"BTC/KRW","side":"buy","price":1000000,"amount":0.0001},{"id":"721459","info":{"date":"1556604266","price":811000,"amount":0.0274,"tid":"721459","type":"sell"},"timestamp":1556604266000,"datetime":"2019-04-30T06:04:26.000Z","symbol":"BTC/KRW","side":"sell","price":811000,"amount":0.0274},{"id":"721460","info":{"date":"1556604478","price":811000,"amount":0.0196,"tid":"721460","type":"buy"},"timestamp":1556604478000,"datetime":"2019-04-30T06:07:58.000Z","symbol":"BTC/KRW","side":"buy","price":811000,"amount":0.0196},{"id":"721461","info":{"date":"1556606694","price":900000,"amount":0.0064,"tid":"721461","type":"sell"},"timestamp":1556606694000,"datetime":"2019-04-30T06:44:54.000Z","symbol":"BTC/KRW","side":"sell","price":900000,"amount":0.0064},{"id":"721462","info":{"date":"1556606700","price":900000,"amount":0.0002,"tid":"721462","type":"buy"},"timestamp":1556606700000,"datetime":"2019-04-30T06:45:00.000Z","symbol":"BTC/KRW","side":"buy","price":900000,"amount":0.0002},{"id":"721463","info":{"date":"1556606700","price":3990000,"amount":0.0023,"tid":"721463","type":"buy"},"timestamp":1556606700000,"datetime":"2019-04-30T06:45:00.000Z","symbol":"BTC/KRW","side":"buy","price":3990000,"amount":0.0023},{"id":"721464","info":{"date":"1556608128","price":3965000,"amount":0.0005,"tid":"721464","type":"buy"},"timestamp":1556608128000,"datetime":"2019-04-30T07:08:48.000Z","symbol":"BTC/KRW","side":"buy","price":3965000,"amount":0.0005},{"id":"721465","info":{"date":"1556608396","price":3963000,"amount":0.0001,"tid":"721465","type":"buy"},"timestamp":1556608396000,"datetime":"2019-04-30T07:13:16.000Z","symbol":"BTC/KRW","side":"buy","price":3963000,"amount":0.0001},{"id":"721466","info":{"date":"1556609692","price":900000,"amount":0.0002,"tid":"721466","type":"buy"},"timestamp":1556609692000,"datetime":"2019-04-30T07:34:52.000Z","symbol":"BTC/KRW","side":"buy","price":900000,"amount":0.0002},{"id":"721467","info":{"date":"1556610699","price":1300000,"amount":0.0002,"tid":"721467","type":"sell"},"timestamp":1556610699000,"datetime":"2019-04-30T07:51:39.000Z","symbol":"BTC/KRW","side":"sell","price":1300000,"amount":0.0002}]}}