{"connect":{"statusCode":200,"response":{"id":"","name":"Kuna","private":false,"enableRateLimit":true,"countries":["UA"],"rateLimit":1000,"has":{"cancelAllOrders":"false","cancelOrder":"true","cancelOrders":"false","CORS":"false","createDepositAddress":"false","createLimitOrder":"true","createMarketOrder":"true","createOrder":"true","deposit":"false","editOrder":"emulated","fetchBalance":"true","fetchBidsAsks":"false","fetchClosedOrders":"false","fetchCurrencies":"false","fetchDepositAddress":"false","fetchDeposits":"false","fetchFundingFees":"false","fetchL2OrderBook":"true","fetchLedger":"false","fetchMarkets":"true","fetchMyTrades":"true","fetchOHLCV":"true","fetchOpenOrders":"true","fetchOrder":"true","fetchOrderBook":"true","fetchOrderBooks":"false","fetchOrders":"false","fetchTicker":"true","fetchTickers":"true","fetchTrades":"true","fetchTradingFee":"false","fetchTradingFees":"false","fetchTradingLimits":"false","fetchTransactions":"false","fetchWithdrawals":"false","privateAPI":"true","publicAPI":"true","withdraw":"false"},"urls":{"logo":"https://user-images.githubusercontent.com/1294454/31697638-912824fa-b3c1-11e7-8c36-cf9606eb94ac.jpg","api":"https://kuna.io","www":"https://kuna.io","doc":"https://kuna.io/documents/api","fees":"https://kuna.io/documents/api","extension":".json"}}},"markets":{"statusCode":200,"response":[{"id":"btcuah","symbol":"BTC/UAH","base":"BTC","quote":"UAH","limits":{"amount":{"min":0.000001,"max":1000000},"price":{"min":1,"max":1},"cost":{}},"precision":{"amount":6,"price":0}},{"id":"golbtc","symbol":"GOL/BTC","base":"GOL","quote":"BTC","limits":{"amount":{"min":0.000001,"max":1000000},"price":{"min":0.000001,"max":1000000},"cost":{}},"precision":{"amount":6,"price":6}},{"id":"ethuah","symbol":"ETH/UAH","base":"ETH","quote":"UAH","limits":{"amount":{"min":0.000001,"max":1000000},"price":{"min":1,"max":1},"cost":{}},"precision":{"amount":6,"price":0}},{"id":"wavesuah","symbol":"WAVES/UAH","base":"WAVES","quote":"UAH","limits":{"amount":{"min":0.000001,"max":1000000},"price":{"min":1,"max":1},"cost":{}},"precision":{"amount":6,"price":0}},{"id":"kunbtc","symbol":"KUN/BTC","base":"KUN","quote":"BTC","limits":{"amount":{"min":0.000001,"max":1000000},"price":{"min":0.000001,"max":1000000},"cost":{}},"precision":{"amount":6,"price":6}},{"id":"bchbtc","symbol":"BCH/BTC","base":"BCH","quote":"BTC","limits":{"amount":{"min":0.000001,"max":1000000},"price":{"min":0.000001,"max":1000000},"cost":{}},"precision":{"amount":6,"price":6}},{"id":"arnbtc","symbol":"ARN/BTC","base":"ARN","quote":"BTC","limits":{"amount":{"min":0.000001,"max":1000000},"price":{"min":0.000001,"max":1000000},"cost":{}},"precision":{"amount":6,"price":6}},{"id":"bchuah","symbol":"BCH/UAH","base":"BCH","quote":"UAH","limits":{"amount":{"min":0.000001,"max":1000000},"price":{"min":1,"max":1},"cost":{}},"precision":{"amount":6,"price":0}},{"id":"xrpuah","symbol":"XRP/UAH","base":"XRP","quote":"UAH","limits":{"amount":{"min":0.000001,"max":1000000},"price":{"min":1,"max":1},"cost":{}},"precision":{"amount":6,"price":0}},{"id":"hknbtc","symbol":"HKN/BTC","base":"HKN","quote":"BTC","limits":{"amount":{"min":0.000001,"max":1000000},"price":{"min":0.000001,"max":1000000},"cost":{}},"precision":{"amount":6,"price":6}},{"id":"xlmuah","symbol":"XLM/UAH","base":"XLM","quote":"UAH","limits":{"amount":{"min":0.000001,"max":1000000},"price":{"min":1,"max":1},"cost":{}},"precision":{"amount":6,"price":0}},{"id":"tusduah","symbol":"TUSD/UAH","base":"TUSD","quote":"UAH","limits":{"amount":{"min":0.000001,"max":1000000},"price":{"min":1,"max":1},"cost":{}},"precision":{"amount":6,"price":0}},{"id":"eosuah","symbol":"EOS/UAH","base":"EOS","quote":"UAH","limits":{"amount":{"min":0.000001,"max":1000000},"price":{"min":1,"max":1},"cost":{}},"precision":{"amount":6,"price":0}},{"id":"ltcuah","symbol":"LTC/UAH","base":"LTC","quote":"UAH","limits":{"amount":{"min":0.000001,"max":1000000},"price":{"min":1,"max":1},"cost":{}},"precision":{"amount":6,"price":0}},{"id":"dashuah","symbol":"DASH/UAH","base":"DASH","quote":"UAH","limits":{"amount":{"min":0.000001,"max":1000000},"price":{"min":1,"max":1},"cost":{}},"precision":{"amount":6,"price":0}},{"id":"zecuah","symbol":"ZEC/UAH","base":"ZEC","quote":"UAH","limits":{"amount":{"min":0.000001,"max":1000000},"price":{"min":1,"max":1},"cost":{}},"precision":{"amount":6,"price":0}},{"id":"xemuah","symbol":"XEM/UAH","base":"XEM","quote":"UAH","limits":{"amount":{"min":0.000001,"max":1000000},"price":{"min":1,"max":1},"cost":{}},"precision":{"amount":6,"price":0}},{"id":"remuah","symbol":"REM/UAH","base":"REM","quote":"UAH","limits":{"amount":{"min":0.000001,"max":1000000},"price":{"min":1,"max":1},"cost":{}},"precision":{"amount":6,"price":0}},{"id":"remeth","symbol":"REM/ETH","base":"REM","quote":"ETH","limits":{"amount":{"min":0.000001,"max":1000000},"price":{"min":0.000001,"max":1000000},"cost":{}},"precision":{"amount":6,"price":6}},{"id":"krbuah","symbol":"KRB/UAH","base":"KRB","quote":"UAH","limits":{"amount":{"min":0.000001,"max":1000000},"price":{"min":1,"max":1},"cost":{}},"precision":{"amount":6,"price":0}},{"id":"eursuah","symbol":"EURS/UAH","base":"EURS","quote":"UAH","limits":{"amount":{"min":0.000001,"max":1000000},"price":{"min":1,"max":1},"cost":{}},"precision":{"amount":6,"price":0}},{"id":"btceurs","symbol":"BTC/EURS","base":"BTC","quote":"EURS","limits":{"amount":{"min":0.000001,"max":1000000},"price":{"min":0.000001,"max":1000000},"cost":{}},"precision":{"amount":6,"price":6}},{"id":"eosbtc","symbol":"EOS/BTC","base":"EOS","quote":"BTC","limits":{"amount":{"min":0.000001,"max":1000000},"price":{"min":0.000001,"max":1000000},"cost":{}},"precision":{"amount":6,"price":6}},{"id":"ethbtc","symbol":"ETH/BTC","base":"ETH","quote":"BTC","limits":{"amount":{"min":0.000001,"max":1000000},"price":{"min":0.000001,"max":1000000},"cost":{}},"precision":{"amount":6,"price":6}},{"id":"usdtuah","symbol":"USDT/UAH","base":"USDT","quote":"UAH","limits":{"amount":{"min":0.000001,"max":1000000},"price":{"min":1,"max":1},"cost":{}},"precision":{"amount":6,"price":0}},{"id":"dreambtc","symbol":"DREAM/BTC","base":"DREAM","quote":"BTC","limits":{"amount":{"min":0.000001,"max":1000000},"price":{"min":0.000001,"max":1000000},"cost":{}},"precision":{"amount":6,"price":6}},{"id":"dreamuah","symbol":"DREAM/UAH","base":"DREAM","quote":"UAH","limits":{"amount":{"min":0.000001,"max":1000000},"price":{"min":1,"max":1},"cost":{}},"precision":{"amount":6,"price":0}}]},"ticker":{"statusCode":200,"response":{"symbol":"BTC/UAH","timestamp":1557723371000,"datetime":"2019-05-13T04:56:11.000Z","high":200896,"low":179217,"bid":183703,"ask":186614,"close":183328,"last":183328,"baseVolume":34.698041,"info":{"buy":"183703.0","sell":"186614.0","low":"179217.0","high":"200896.0","last":"183328.0","vol":"34.698041","price":"6621563.245855"}}},"tickers":{"statusCode":200,"response":[{"symbol":"ARN/BTC","timestamp":1557723372000,"datetime":"2019-05-13T04:56:12.000Z","high":0.000062,"low":0.000054,"bid":0.000053,"ask":0.000063,"close":0.000058,"last":0.000058,"baseVolume":6265.855435,"info":{"buy":"0.000053","sell":"0.000063","low":"0.000054","high":"0.000062","last":"0.000058","vol":"6265.855435","price":"0.351346688958"}},{"symbol":"BCH/BTC","timestamp":1557723372000,"datetime":"2019-05-13T04:56:12.000Z","high":0.055341,"low":0.042999,"bid":0.043608,"ask":0.056599,"close":0.055341,"last":0.055341,"baseVolume":0.158376,"info":{"buy":"0.043608","sell":"0.056599","low":"0.042999","high":"0.055341","last":"0.055341","vol":"0.158376","price":"0.007935597445"}},{"symbol":"BCH/UAH","timestamp":1557723372000,"datetime":"2019-05-13T04:56:12.000Z","high":9920,"low":8150,"bid":9061,"ask":9599,"close":9577,"last":9577,"baseVolume":24.982563,"info":{"buy":"9061.0","sell":"9599.0","low":"8150.0","high":"9920.0","last":"9577.0","vol":"24.982563","price":"233105.934648"}},{"symbol":"BTC/EURS","timestamp":1557723372000,"datetime":"2019-05-13T04:56:12.000Z","high":5936.74,"low":5766.21,"bid":5241.02,"ask":6992.3,"close":5936.74,"last":5936.74,"baseVolume":0,"info":{"buy":"5241.02","sell":"6992.3","low":"5766.21","high":"5936.74","last":"5936.74","vol":"0.0","price":0}},{"timestamp":1557723372000,"datetime":"2019-05-13T04:56:12.000Z","high":482092.69,"low":474900,"bid":415781.72,"ask":481808.16,"close":482092.69,"last":482092.69,"baseVolume":0.031114,"info":{"buy":"415781.72","sell":"481808.16","low":"474900.0","high":"482092.69","last":"482092.69","vol":"0.031114","price":"14999.83195666"}},{"symbol":"BTC/UAH","timestamp":1557723372000,"datetime":"2019-05-13T04:56:12.000Z","high":200896,"low":179217,"bid":183703,"ask":186614,"close":183328,"last":183328,"baseVolume":34.698041,"info":{"buy":"183703.0","sell":"186614.0","low":"179217.0","high":"200896.0","last":"183328.0","vol":"34.698041","price":"6621563.245855"}},{"timestamp":1557723372000,"datetime":"2019-05-13T04:56:12.000Z","high":7800,"low":6800,"bid":6800,"ask":7200,"close":6800,"last":6800,"baseVolume":0.03326,"info":{"buy":"6800.0","sell":"7200.0","low":"6800.0","high":"7800.0","last":"6800.0","vol":"0.03326","price":"236.23051396"}},{"symbol":"DASH/UAH","timestamp":1557723372000,"datetime":"2019-05-13T04:56:12.000Z","high":3395,"low":3131,"bid":3295,"ask":3395,"close":3395,"last":3395,"baseVolume":5.6098,"info":{"buy":"3295.0","sell":"3395.0","low":"3131.0","high":"3395.0","last":"3395.0","vol":"5.6098","price":"18370.0958"}},{"symbol":"DREAM/BTC","timestamp":1557723372000,"datetime":"2019-05-13T04:56:12.000Z","high":0.00001102,"low":0.00000802,"bid":0.00000803,"ask":0.00001789,"close":0.00000802,"last":0.00000802,"baseVolume":4039.087466,"info":{"buy":"0.00000803","sell":"0.00001789","low":"0.00000802","high":"0.00001102","last":"0.00000802","vol":"4039.087466","price":"0.03676489004708"}},{"symbol":"DREAM/UAH","timestamp":1557723372000,"datetime":"2019-05-13T04:56:12.000Z","high":2.85,"low":2.75,"bid":2.71,"ask":2.77,"close":2.76,"last":2.76,"baseVolume":14646.830432,"info":{"buy":"2.71","sell":"2.77","low":"2.75","high":"2.85","last":"2.76","vol":"14646.830432","price":"40921.77780383"}},{"symbol":"EOS/BTC","timestamp":1557723372000,"datetime":"2019-05-13T04:56:12.000Z","high":0.00076,"low":0.000708,"bid":0.000708,"ask":0.000763,"close":0.000708,"last":0.000708,"baseVolume":5.461157,"info":{"buy":"0.000708","sell":"0.000763","low":"0.000708","high":"0.00076","last":"0.000708","vol":"5.461157","price":"0.004002448876"}},{"symbol":"EOS/UAH","timestamp":1557723372000,"datetime":"2019-05-13T04:56:12.000Z","high":150,"low":138.1,"bid":140.73,"ask":144.48,"close":141.01,"last":141.01,"baseVolume":575.492821,"info":{"buy":"140.73","sell":"144.48","low":"138.1","high":"150.0","last":"141.01","vol":"575.492821","price":"84018.19564802"}},{"symbol":"ETH/BTC","timestamp":1557723372000,"datetime":"2019-05-13T04:56:12.000Z","high":0.027042,"low":0.025056,"bid":0.026142,"ask":0.027599,"close":0.026839,"last":0.026839,"baseVolume":11.896233,"info":{"buy":"0.026142","sell":"0.027599","low":"0.025056","high":"0.027042","last":"0.026839","vol":"11.896233","price":"0.315932916123"}},{"symbol":"ETH/UAH","timestamp":1557723372000,"datetime":"2019-05-13T04:56:12.000Z","high":5294,"low":4800,"bid":4989,"ask":5044,"close":5011,"last":5011,"baseVolume":378.228936,"info":{"buy":"4989.0","sell":"5044.0","low":"4800.0","high":"5294.0","last":"5011.0","vol":"378.228936","price":"1899168.552136"}},{"symbol":"EURS/UAH","timestamp":1557723372000,"datetime":"2019-05-13T04:56:12.000Z","high":28.08,"low":28.08,"bid":28.11,"ask":30.12,"close":28.08,"last":28.08,"baseVolume":3.65,"info":{"buy":"28.11","sell":"30.12","low":"28.08","high":"28.08","last":"28.08","vol":"3.65","price":"102.492"}},{"timestamp":1557723372000,"datetime":"2019-05-13T04:56:12.000Z","high":0.0095,"low":0.0073,"bid":0.0089,"ask":0.008998,"close":0.008998,"last":0.008998,"baseVolume":2913.286,"info":{"buy":"0.0089","sell":"0.008998","low":"0.0073","high":"0.0095","last":"0.008998","vol":"2913.286","price":"24.949443402"}},{"symbol":"GOL/BTC","timestamp":1557723372000,"datetime":"2019-05-13T04:56:12.000Z","high":7e-7,"low":4e-7,"bid":5e-7,"ask":6e-7,"close":5e-7,"last":5e-7,"baseVolume":11070.903,"info":{"buy":"0.0000005","sell":"0.0000006","low":"0.0000004","high":"0.0000007","last":"0.0000005","vol":"11070.903","price":"0.00577635755"}},{"symbol":"HKN/BTC","timestamp":1557723372000,"datetime":"2019-05-13T04:56:12.000Z","high":0,"low":0,"bid":0.00004,"ask":0.000054,"close":0.000039,"last":0.000039,"baseVolume":0,"info":{"buy":"0.00004","sell":"0.000054","low":"0.0","high":"0.0","last":"0.000039","vol":"0.0","price":0}},{"symbol":"KRB/UAH","timestamp":1557723372000,"datetime":"2019-05-13T04:56:12.000Z","high":2.67,"low":2.39,"bid":2.41,"ask":2.48,"close":2.39,"last":2.39,"baseVolume":1740.8579,"info":{"buy":"2.41","sell":"2.48","low":"2.39","high":"2.67","last":"2.39","vol":"1740.8579","price":"4341.796261"}},{"symbol":"KUN/BTC","timestamp":1557723372000,"datetime":"2019-05-13T04:56:12.000Z","high":0.000794,"low":0.00066,"bid":0.000701,"ask":0.000818,"close":0.000753,"last":0.000753,"baseVolume":1296,"info":{"buy":"0.000701","sell":"0.000818","low":"0.00066","high":"0.000794","last":"0.000753","vol":"1296.0","price":"0.94687"}},{"symbol":"LTC/UAH","timestamp":1557723372000,"datetime":"2019-05-13T04:56:12.000Z","high":2453,"low":2170,"bid":2204,"ask":2255,"close":2255,"last":2255,"baseVolume":121.8206,"info":{"buy":"2204.0","sell":"2255.0","low":"2170.0","high":"2453.0","last":"2255.0","vol":"121.8206","price":"286817.4396"}},{"symbol":"REM/ETH","timestamp":1557723372000,"datetime":"2019-05-13T04:56:12.000Z","high":0.00002803,"low":0.00002707,"bid":0.00002707,"ask":0.00003799,"close":0.00002722,"last":0.00002722,"baseVolume":90185.3563,"info":{"buy":"0.00002707","sell":"0.00003799","low":"0.00002707","high":"0.00002803","last":"0.00002722","vol":"90185.3563","price":"2.479378695041"}},{"symbol":"REM/UAH","timestamp":1557723372000,"datetime":"2019-05-13T04:56:12.000Z","high":0.147,"low":0.132,"bid":0.132,"ask":0.1457,"close":0.1387,"last":0.1387,"baseVolume":111358.858771,"info":{"buy":"0.132","sell":"0.1457","low":"0.132","high":"0.147","last":"0.1387","vol":"111358.858771","price":"15456.0410958864"}},{"symbol":"TUSD/UAH","timestamp":1557723372000,"datetime":"2019-05-13T04:56:12.000Z","high":26.47,"low":25.89,"bid":26.02,"ask":26.43,"close":26.43,"last":26.43,"baseVolume":456.32,"info":{"buy":"26.02","sell":"26.43","low":"25.89","high":"26.47","last":"26.43","vol":"456.32","price":"12013.0268"}},{"timestamp":1557723372000,"datetime":"2019-05-13T04:56:12.000Z","high":66.87,"low":64,"bid":64,"ask":67.5,"close":65.99,"last":65.99,"baseVolume":320.27,"info":{"buy":"64.0","sell":"67.5","low":"64.0","high":"66.87","last":"65.99","vol":"320.27","price":"21121.8561"}},{"symbol":"USDT/UAH","timestamp":1557723372000,"datetime":"2019-05-13T04:56:12.000Z","high":26.63,"low":25.72,"bid":26.18,"ask":26.61,"close":26.62,"last":26.62,"baseVolume":35791.77,"info":{"buy":"26.18","sell":"26.61","low":"25.72","high":"26.63","last":"26.62","vol":"35791.77","price":"947876.0251"}},{"symbol":"WAVES/UAH","timestamp":1557723372000,"datetime":"2019-05-13T04:56:12.000Z","high":66,"low":56,"bid":61,"ask":64,"close":64,"last":64,"baseVolume":2113.429348,"info":{"buy":"61.0","sell":"64.0","low":"56.0","high":"66.0","last":"64.0","vol":"2113.429348","price":"128864.962159"}},{"symbol":"XEM/UAH","timestamp":1557723372000,"datetime":"2019-05-13T04:56:12.000Z","high":1.64,"low":1.5,"bid":1.52,"ask":1.54,"close":1.52,"last":1.52,"baseVolume":61893.6617,"info":{"buy":"1.52","sell":"1.54","low":"1.5","high":"1.64","last":"1.52","vol":"61893.6617","price":"97956.74284"}},{"symbol":"XLM/UAH","timestamp":1557723372000,"datetime":"2019-05-13T04:56:12.000Z","high":3.03,"low":2.4,"bid":2.58,"ask":2.61,"close":2.57,"last":2.57,"baseVolume":91480.168737,"info":{"buy":"2.58","sell":"2.61","low":"2.4","high":"3.03","last":"2.57","vol":"91480.168737","price":"241642.43469145"}},{"symbol":"XRP/UAH","timestamp":1557723372000,"datetime":"2019-05-13T04:56:12.000Z","high":8.64,"low":8.13,"bid":8.33,"ask":8.44,"close":8.44,"last":8.44,"baseVolume":66609.6012,"info":{"buy":"8.33","sell":"8.44","low":"8.13","high":"8.64","last":"8.44","vol":"66609.6012","price":"557197.687827"}},{"symbol":"ZEC/UAH","timestamp":1557723372000,"datetime":"2019-05-13T04:56:12.000Z","high":1737,"low":1571,"bid":1596,"ask":1659,"close":1589,"last":1589,"baseVolume":54.6908,"info":{"buy":"1596.0","sell":"1659.0","low":"1571.0","high":"1737.0","last":"1589.0","vol":"54.6908","price":"92127.4576"}}]},"orderBook":{"statusCode":200,"response":{"bids":[{"price":183703,"amount":0.001343},{"price":183702,"amount":0.05},{"price":183700,"amount":4.514463},{"price":183377,"amount":0.00289},{"price":183153,"amount":0.187467},{"price":183126,"amount":0.001},{"price":183100,"amount":0.014041},{"price":182998,"amount":0.005924},{"price":182783,"amount":0.004},{"price":182383,"amount":0.001233},{"price":182076,"amount":0.152839},{"price":182001,"amount":0.888379},{"price":181000,"amount":0.007856},{"price":180102,"amount":0.001},{"price":180101,"amount":0.01},{"price":180000,"amount":0.003332},{"price":179977,"amount":0.005934},{"price":179957,"amount":0.008},{"price":179769,"amount":0.001},{"price":179470,"amount":0.01},{"price":179215,"amount":0.001},{"price":179150,"amount":0.005},{"price":178826,"amount":0.00223},{"price":178650,"amount":0.006},{"price":178150,"amount":0.007},{"price":178055,"amount":0.015163},{"price":178000,"amount":0.560438},{"price":177777,"amount":0.002863},{"price":177650,"amount":0.008},{"price":177501,"amount":0.005616},{"price":177151,"amount":0.001},{"price":177150,"amount":0.009},{"price":177130,"amount":0.016},{"price":177100,"amount":0.045},{"price":176103,"amount":0.005678},{"price":175500,"amount":0.03},{"price":175342,"amount":0.001},{"price":175249,"amount":0.001255},{"price":175150,"amount":0.01},{"price":175011,"amount":0.001714},{"price":175007,"amount":0.025},{"price":175000,"amount":0.334553},{"price":174947,"amount":0.001003},{"price":174596,"amount":0.000687},{"price":174305,"amount":0.001},{"price":174304,"amount":0.032},{"price":174125,"amount":0.017241},{"price":174005,"amount":0.027148},{"price":173150,"amount":0.011},{"price":173003,"amount":0.146355},{"price":173000,"amount":0.017855},{"price":172777,"amount":0.15},{"price":172127,"amount":0.084},{"price":172017,"amount":0.01744},{"price":172000,"amount":0.091034},{"price":171744,"amount":0.00128},{"price":171667,"amount":0.001},{"price":171666,"amount":0.00291},{"price":171477,"amount":0.064},{"price":171150,"amount":0.012},{"price":171000,"amount":0.004853},{"price":170000,"amount":0.010687},{"price":169999,"amount":0.003},{"price":169150,"amount":0.013},{"price":168889,"amount":0.001},{"price":168888,"amount":0.06221},{"price":168651,"amount":0.128},{"price":168571,"amount":0.5},{"price":168310,"amount":0.001307},{"price":168000,"amount":0.025255},{"price":167777,"amount":0.003},{"price":167560,"amount":0.08},{"price":167477,"amount":0.008938},{"price":166989,"amount":0.0187},{"price":166666,"amount":0.003},{"price":166555,"amount":0.048032},{"price":166201,"amount":0.00005},{"price":166151,"amount":0.001},{"price":166150,"amount":0.014},{"price":165824,"amount":0.198},{"price":165555,"amount":0.000302},{"price":165489,"amount":0.000302},{"price":165000,"amount":0.007884},{"price":164943,"amount":0.001351},{"price":164820,"amount":1.2},{"price":164000,"amount":0.052359},{"price":163463,"amount":0.001003},{"price":163150,"amount":0.015},{"price":162445,"amount":0.00336},{"price":162322,"amount":0.19},{"price":162147,"amount":0.000055},{"price":161079,"amount":1},{"price":160690,"amount":0.00334},{"price":160456,"amount":0.00337},{"price":160150,"amount":0.016},{"price":160006,"amount":0.003},{"price":160000,"amount":0.166431},{"price":159754,"amount":0.00335},{"price":159701,"amount":0.087657},{"price":159000,"amount":0.1},{"price":158888,"amount":0.001},{"price":158380,"amount":0.0166},{"price":158193,"amount":0.00006},{"price":158100,"amount":0.001},{"price":158000,"amount":0.05612},{"price":157906,"amount":0.003},{"price":157510,"amount":0.014722},{"price":157400,"amount":0.000635},{"price":157000,"amount":0.110484},{"price":156989,"amount":0.03},{"price":156432,"amount":0.00332},{"price":156203,"amount":0.004231},{"price":156150,"amount":0.09},{"price":156060,"amount":0.02},{"price":156000,"amount":0.105529},{"price":155777,"amount":0.003569},{"price":155756,"amount":0.002096},{"price":155678,"amount":0.001003},{"price":155656,"amount":0.002098},{"price":155586,"amount":0.000321},{"price":155556,"amount":0.002099},{"price":155555,"amount":0.003},{"price":155220,"amount":0.08},{"price":155165,"amount":0.007862},{"price":155075,"amount":0.001772},{"price":155030,"amount":0.090305},{"price":155000,"amount":0.126},{"price":154946,"amount":0.00331},{"price":154766,"amount":0.054592},{"price":154594,"amount":0.002},{"price":154334,"amount":0.000065},{"price":154000,"amount":0.1},{"price":153800,"amount":0.001534},{"price":153735,"amount":0.003597},{"price":153587,"amount":1.5},{"price":153000,"amount":0.1},{"price":152784,"amount":0.001},{"price":152502,"amount":0.005},{"price":152401,"amount":0.004593},{"price":152295,"amount":0.0033},{"price":152000,"amount":0.032894},{"price":151888,"amount":0.005852},{"price":151147,"amount":0.00333},{"price":151000,"amount":0.11},{"price":150570,"amount":0.00007},{"price":150250,"amount":0.001},{"price":150002,"amount":0.010013},{"price":150000,"amount":0.263645},{"price":149888,"amount":0.007418},{"price":149532,"amount":0.00675},{"price":149050,"amount":0.001682},{"price":149000,"amount":0.1},{"price":148999,"amount":0.003731},{"price":148574,"amount":0.00675},{"price":148555,"amount":0.008979},{"price":148457,"amount":0.0035},{"price":148300,"amount":0.002},{"price":148010,"amount":0.003932},{"price":148000,"amount":1.111498},{"price":147777,"amount":0.014359},{"price":147601,"amount":0.01},{"price":147507,"amount":0.01},{"price":147500,"amount":0.001},{"price":147357,"amount":0.00475},{"price":147314,"amount":0.001003},{"price":147101,"amount":0.002039},{"price":147000,"amount":0.139074},{"price":146989,"amount":0.03},{"price":146500,"amount":0.095542},{"price":146274,"amount":0.132451},{"price":146095,"amount":2},{"price":146000,"amount":0.109171},{"price":145555,"amount":0.014452},{"price":145333,"amount":0.014786},{"price":145200,"amount":0.00355},{"price":145090,"amount":0.0264},{"price":145000,"amount":0.21191},{"price":144888,"amount":0.012271},{"price":144500,"amount":0.00346},{"price":144444,"amount":0.003},{"price":144044,"amount":0.003089},{"price":143350,"amount":0.000767},{"price":143333,"amount":0.003097},{"price":143000,"amount":0.007},{"price":142851,"amount":0.003108},{"price":142777,"amount":0.002325},{"price":142000,"amount":0.083449},{"price":141957,"amount":0.00675},{"price":141777,"amount":0.005487},{"price":141711,"amount":0.001003},{"price":141555,"amount":0.007855},{"price":141500,"amount":0.004},{"price":141444,"amount":0.003923},{"price":141150,"amount":0.005},{"price":141111,"amount":0.013386},{"price":141000,"amount":0.008599},{"price":140851,"amount":0.00394},{"price":140800,"amount":0.1},{"price":140777,"amount":0.0268},{"price":140650,"amount":0.006},{"price":140150,"amount":0.008},{"price":140140,"amount":0.252112},{"price":140002,"amount":0.001},{"price":140001,"amount":0.005},{"price":140000,"amount":0.13585},{"price":139851,"amount":0.004061},{"price":139650,"amount":0.01},{"price":138983,"amount":0.001003},{"price":138000,"amount":0.014217},{"price":137888,"amount":0.006447},{"price":137574,"amount":0.003816},{"price":137507,"amount":0.001},{"price":137450,"amount":0.001091},{"price":137000,"amount":0.01159},{"price":136379,"amount":0.00101},{"price":136001,"amount":0.00597},{"price":136000,"amount":9.095588},{"price":135220,"amount":0.2},{"price":135005,"amount":0.029628},{"price":135000,"amount":0.01},{"price":134688,"amount":0.014106},{"price":133333,"amount":0.009262},{"price":133029,"amount":0.003758},{"price":133000,"amount":0.009},{"price":132000,"amount":0.226689},{"price":131508,"amount":0.002281},{"price":131000,"amount":0.01},{"price":130999,"amount":0.007633},{"price":130500,"amount":0.5},{"price":130300,"amount":0.00833},{"price":130000,"amount":0.094584},{"price":129851,"amount":0.005128},{"price":129000,"amount":0.012356},{"price":128210,"amount":0.02},{"price":128076,"amount":0.001003},{"price":128000,"amount":0.01},{"price":127777,"amount":0.006088},{"price":127005,"amount":0.1},{"price":127000,"amount":0.01},{"price":126945,"amount":0.00972},{"price":126888,"amount":0.007006},{"price":126623,"amount":0.002621},{"price":126222,"amount":0.007922},{"price":126111,"amount":0.006169},{"price":126000,"amount":0.01},{"price":125777,"amount":0.008841},{"price":125605,"amount":0.040789},{"price":125600,"amount":0.015031},{"price":125555,"amount":0.007964},{"price":125450,"amount":0.003547},{"price":125106,"amount":0.001598},{"price":125018,"amount":0.003999},{"price":125005,"amount":0.001},{"price":125000,"amount":0.01},{"price":124777,"amount":0.004463},{"price":124555,"amount":0.009915},{"price":124444,"amount":0.002667},{"price":124000,"amount":0.01},{"price":123000,"amount":0.01},{"price":122888,"amount":0.007234},{"price":122451,"amount":0.007251},{"price":122000,"amount":0.01},{"price":121978,"amount":0.001003},{"price":121688,"amount":0.016435},{"price":121508,"amount":0.057609},{"price":121000,"amount":0.01},{"price":120555,"amount":0.006047},{"price":120271,"amount":0.008314},{"price":120000,"amount":0.0168},{"price":119000,"amount":0.01},{"price":118800,"amount":0.064},{"price":118200,"amount":0.006},{"price":118000,"amount":0.01},{"price":117000,"amount":0.01594},{"price":116344,"amount":0.007649},{"price":116200,"amount":0.01},{"price":116168,"amount":0.001003},{"price":116000,"amount":0.01},{"price":115600,"amount":0.02},{"price":115555,"amount":0.004811},{"price":115000,"amount":0.03},{"price":114000,"amount":0.01},{"price":113717,"amount":0.026029},{"price":113455,"amount":0.000361},{"price":113430,"amount":0.021502},{"price":113201,"amount":0.183567},{"price":113123,"amount":0.004685},{"price":113000,"amount":0.01},{"price":112777,"amount":0.004921},{"price":112500,"amount":0.001},{"price":112200,"amount":0.022281},{"price":112000,"amount":0.047097},{"price":111821,"amount":0.02},{"price":111666,"amount":0.00694},{"price":111355,"amount":0.004497},{"price":111300,"amount":0.013477},{"price":111000,"amount":0.024306},{"price":110637,"amount":0.001003},{"price":110631,"amount":0.008026},{"price":110381,"amount":0.0031}],"asks":[{"price":186614,"amount":0.037689},{"price":186615,"amount":0.026666},{"price":186616,"amount":0.0049},{"price":186700,"amount":0.000538},{"price":186750,"amount":0.005},{"price":186872,"amount":0.000997},{"price":186974,"amount":0.000904},{"price":187319,"amount":0.000006},{"price":187327,"amount":0.000005},{"price":187523,"amount":0.001793},{"price":187535,"amount":0.001907},{"price":187890,"amount":0.005},{"price":188321,"amount":0.000037},{"price":188322,"amount":0.000071},{"price":188521,"amount":0.000013},{"price":188523,"amount":0.000098},{"price":188526,"amount":0.000007},{"price":188527,"amount":0.000076},{"price":188534,"amount":0.000003},{"price":188535,"amount":0.000003},{"price":188788,"amount":0.001},{"price":188789,"amount":0.001},{"price":188917,"amount":0.00488},{"price":189049,"amount":0.001072},{"price":189127,"amount":0.000188},{"price":189154,"amount":0.000139},{"price":189457,"amount":0.012789},{"price":189874,"amount":0.000995},{"price":189900,"amount":0.035621},{"price":189924,"amount":0.021178},{"price":189939,"amount":0.020042},{"price":190000,"amount":0.146422},{"price":191000,"amount":0.03},{"price":191100,"amount":0.024993},{"price":191500,"amount":0.013021},{"price":191990,"amount":0.03},{"price":191999,"amount":0.03},{"price":192000,"amount":0.026261},{"price":192997,"amount":0.00088},{"price":193400,"amount":0.049045},{"price":193450,"amount":0.02},{"price":194001,"amount":0.00525},{"price":194620,"amount":0.001009},{"price":194900,"amount":0.003995},{"price":195000,"amount":0.38428},{"price":195209,"amount":0.06},{"price":196000,"amount":0.026152},{"price":196100,"amount":0.002701},{"price":196500,"amount":0.086309},{"price":196800,"amount":0.029318},{"price":196888,"amount":0.078201},{"price":197100,"amount":0.000101},{"price":197200,"amount":0.002039},{"price":198000,"amount":0.027426},{"price":198100,"amount":0.0001},{"price":198339,"amount":0.006},{"price":198540,"amount":0.017716},{"price":198650,"amount":0.15},{"price":198716,"amount":0.001},{"price":198750,"amount":0.09},{"price":199000,"amount":0.02},{"price":199100,"amount":0.133756},{"price":199500,"amount":0.060239},{"price":199900,"amount":0.08599},{"price":199987,"amount":0.264125},{"price":199990,"amount":0.019638},{"price":199998,"amount":0.008056},{"price":199999,"amount":0.01},{"price":200000,"amount":0.346181},{"price":200001,"amount":0.014116},{"price":200100,"amount":0.005972},{"price":200267,"amount":0.437},{"price":200800,"amount":0.001874},{"price":201000,"amount":0.02},{"price":201100,"amount":0.011099},{"price":201438,"amount":0.002},{"price":201536,"amount":0.014101},{"price":202100,"amount":0.022198},{"price":202222,"amount":0.02671},{"price":202312,"amount":0.000494},{"price":202345,"amount":0.004185},{"price":202690,"amount":0.001154},{"price":203000,"amount":0.013703},{"price":203100,"amount":0.018896},{"price":203689,"amount":0.028856},{"price":204000,"amount":0.163763},{"price":204100,"amount":0.000097},{"price":204111,"amount":0.12},{"price":204278,"amount":0.000489},{"price":204782,"amount":0.002155},{"price":205000,"amount":0.325654},{"price":205100,"amount":0.000097},{"price":205107,"amount":0.016333},{"price":205403,"amount":0.15},{"price":205500,"amount":0.135547},{"price":205800,"amount":0.052688},{"price":206000,"amount":0.048041},{"price":206100,"amount":0.000097},{"price":206440,"amount":0.5},{"price":207056,"amount":0.00411},{"price":207100,"amount":0.000096},{"price":207300,"amount":0.00367},{"price":207600,"amount":0.01},{"price":208000,"amount":0.05},{"price":208099,"amount":0.005},{"price":208100,"amount":0.000096},{"price":209000,"amount":0.00244},{"price":209100,"amount":0.000095},{"price":209150,"amount":0.01},{"price":209397,"amount":0.9},{"price":209850,"amount":0.011},{"price":209890,"amount":0.05},{"price":209990,"amount":0.00455},{"price":210000,"amount":0.17564},{"price":210100,"amount":0.000095},{"price":210629,"amount":0.02},{"price":210754,"amount":0.038},{"price":210970,"amount":0.01519},{"price":210995,"amount":0.0002},{"price":211100,"amount":0.000094},{"price":212000,"amount":0.013916},{"price":212100,"amount":0.000094},{"price":212333,"amount":0.15},{"price":212750,"amount":0.039},{"price":213100,"amount":0.000093},{"price":213131,"amount":0.05},{"price":213499,"amount":0.005035},{"price":214000,"amount":0.00007},{"price":214300,"amount":0.00514},{"price":214800,"amount":0.0015},{"price":214948,"amount":0.004},{"price":215000,"amount":0.045238},{"price":215800,"amount":0.002},{"price":215807,"amount":0.027},{"price":216000,"amount":0.002784},{"price":216799,"amount":0.053898},{"price":217000,"amount":0.001},{"price":217011,"amount":1.8},{"price":219990,"amount":0.000233},{"price":219996,"amount":0.00235},{"price":220000,"amount":0.802557},{"price":220200,"amount":0.01122},{"price":222000,"amount":0.00764},{"price":222222,"amount":0.001},{"price":224626,"amount":2.699999},{"price":225000,"amount":0.01},{"price":225700,"amount":0.000026},{"price":229000,"amount":0.011},{"price":229097,"amount":0.00125},{"price":229800,"amount":0.003042},{"price":229922,"amount":0.001436},{"price":229999,"amount":0.0407},{"price":230000,"amount":0.048376},{"price":231000,"amount":0.001},{"price":231499,"amount":0.001295},{"price":232240,"amount":3.6},{"price":232323,"amount":0.002},{"price":234000,"amount":0.00125},{"price":235000,"amount":0.020236},{"price":238300,"amount":0.004029},{"price":238400,"amount":0.000524},{"price":238505,"amount":0.03},{"price":238525,"amount":0.001567},{"price":239000,"amount":0.0645},{"price":240000,"amount":0.267739},{"price":242424,"amount":0.001},{"price":242589,"amount":0.000043},{"price":245000,"amount":0.0012},{"price":246644,"amount":0.000309},{"price":248000,"amount":0.002306},{"price":249400,"amount":0.01062},{"price":249444,"amount":0.003479},{"price":249500,"amount":0.001},{"price":250000,"amount":0.71437},{"price":250800,"amount":0.009109},{"price":250993,"amount":0.00092},{"price":251600,"amount":0.00833},{"price":252525,"amount":0.00223},{"price":255000,"amount":0.03377},{"price":255600,"amount":0.0018},{"price":256754,"amount":0.003},{"price":257450,"amount":0.00185},{"price":259000,"amount":0.028515},{"price":259444,"amount":0.004978},{"price":259999,"amount":0.00811},{"price":260000,"amount":0.011798},{"price":260050,"amount":0.033586},{"price":262000,"amount":0.01845},{"price":262865,"amount":0.233297},{"price":264249,"amount":0.0026},{"price":265412,"amount":0.000314},{"price":265438,"amount":0.004828},{"price":268000,"amount":0.00619},{"price":269990,"amount":0.00297},{"price":270000,"amount":0.000125},{"price":272000,"amount":0.007352},{"price":274500,"amount":0.001},{"price":279999,"amount":0.383176},{"price":280000,"amount":0.008739},{"price":281990,"amount":0.011099},{"price":283300,"amount":0.004022},{"price":284000,"amount":0.002228},{"price":289600,"amount":0.00506},{"price":291800,"amount":0.020566},{"price":295900,"amount":0.002},{"price":296000,"amount":0.003655},{"price":298300,"amount":0.004928},{"price":298976,"amount":0.003369},{"price":299000,"amount":0.01015},{"price":299500,"amount":0.003196},{"price":299999,"amount":0.296679},{"price":300000,"amount":0.469892},{"price":300850,"amount":0.004703},{"price":302000,"amount":0.040058},{"price":303000,"amount":0.000343},{"price":305204,"amount":0.003555},{"price":306000,"amount":0.00695},{"price":308500,"amount":0.01339},{"price":308999,"amount":0.000323},{"price":309000,"amount":0.025},{"price":310000,"amount":0.028798},{"price":311990,"amount":0.051587},{"price":315000,"amount":0.0218},{"price":315500,"amount":0.003763},{"price":319800,"amount":0.01},{"price":320000,"amount":0.193316},{"price":320421,"amount":0.1},{"price":320900,"amount":0.046},{"price":321000,"amount":0.000343},{"price":324900,"amount":0.003406},{"price":330000,"amount":0.016915},{"price":333000,"amount":0.003969},{"price":333333,"amount":0.004728},{"price":335000,"amount":0.000027},{"price":339700,"amount":0.0629},{"price":340000,"amount":0.018544},{"price":342355,"amount":0.0676},{"price":342921,"amount":0.050645},{"price":345000,"amount":0.020028},{"price":349500,"amount":0.0025},{"price":350000,"amount":0.237896},{"price":350005,"amount":0.021},{"price":351444,"amount":0.095795},{"price":352000,"amount":0.005681},{"price":356000,"amount":0.002919},{"price":360000,"amount":0.112475},{"price":362888,"amount":0.013},{"price":363000,"amount":0.000611},{"price":364994,"amount":0.002065},{"price":365000,"amount":0.002778},{"price":368962,"amount":0.02},{"price":374000,"amount":0.02463},{"price":380000,"amount":0.183213},{"price":382998,"amount":0.003537},{"price":385000,"amount":0.026599},{"price":388950,"amount":0.074691},{"price":390000,"amount":0.050636},{"price":394380,"amount":0.097526},{"price":398888,"amount":0.0039},{"price":399500,"amount":0.0025},{"price":399995,"amount":0.005},{"price":400000,"amount":0.06267},{"price":402999,"amount":0.013916},{"price":405000,"amount":0.002473},{"price":410000,"amount":0.053512},{"price":410200,"amount":0.01},{"price":412000,"amount":0.01},{"price":413300,"amount":0.002662},{"price":414000,"amount":0.05},{"price":419997,"amount":0.0021},{"price":420000,"amount":0.049811},{"price":421000,"amount":0.002421},{"price":422000,"amount":0.003244},{"price":425050,"amount":0.068665},{"price":426997,"amount":0.0027},{"price":428950,"amount":0.004479},{"price":429000,"amount":0.00491},{"price":430000,"amount":0.006521},{"price":440000,"amount":0.055},{"price":444998,"amount":0.0012},{"price":445000,"amount":0.001631},{"price":448000,"amount":0.031104},{"price":449500,"amount":0.002},{"price":450000,"amount":0.006693},{"price":454900,"amount":0.01},{"price":455100,"amount":0.002252},{"price":458000,"amount":0.00466},{"price":460000,"amount":0.026672},{"price":465500,"amount":0.020555},{"price":469499,"amount":0.068295},{"price":469900,"amount":0.001689},{"price":470000,"amount":0.024553},{"price":471670,"amount":0.050398},{"price":472000,"amount":0.006832},{"price":472400,"amount":0.00226},{"price":478000,"amount":0.030922},{"price":478989,"amount":0.02},{"price":480000,"amount":0.002208},{"price":482997,"amount":0.00145},{"price":483000,"amount":0.020706}],"timestamp":1557723373000,"datetime":"2019-05-13T04:56:13.000Z"}},"trades":{"statusCode":200,"response":[{"id":"2427140","info":{"id":2427140,"price":"185001.0","volume":"0.000156","funds":"28.860156","market":"btcuah","created_at":"2019-05-13T02:37:22Z","side":null,"trend":"sell"},"timestamp":1557715042000,"datetime":"2019-05-13T02:37:22.000Z","symbol":"BTC/UAH","price":185001,"amount":0.000156},{"id":"2427142","info":{"id":2427142,"price":"185000.0","volume":"0.019907","funds":"3682.795","market":"btcuah","created_at":"2019-05-13T02:37:28Z","side":null,"trend":"sell"},"timestamp":1557715048000,"datetime":"2019-05-13T02:37:28.000Z","symbol":"BTC/UAH","price":185000,"amount":0.019907},{"id":"2427146","info":{"id":2427146,"price":"185000.0","volume":"0.001278","funds":"236.43","market":"btcuah","created_at":"2019-05-13T02:43:26Z","side":null,"trend":"sell"},"timestamp":1557715406000,"datetime":"2019-05-13T02:43:26.000Z","symbol":"BTC/UAH","price":185000,"amount":0.001278},{"id":"2427159","info":{"id":2427159,"price":"185328.0","volume":"0.001","funds":"185.328","market":"btcuah","created_at":"2019-05-13T03:26:01Z","side":null,"trend":"sell"},"timestamp":1557717961000,"datetime":"2019-05-13T03:26:01.000Z","symbol":"BTC/UAH","price":185328,"amount":0.001},{"id":"2427166","info":{"id":2427166,"price":"185000.0","volume":"0.001287","funds":"238.095","market":"btcuah","created_at":"2019-05-13T03:46:20Z","side":null,"trend":"sell"},"timestamp":1557719180000,"datetime":"2019-05-13T03:46:20.000Z","symbol":"BTC/UAH","price":185000,"amount":0.001287},{"id":"2427168","info":{"id":2427168,"price":"186160.0","volume":"0.006249","funds":"1163.31384","market":"btcuah","created_at":"2019-05-13T03:48:48Z","side":null,"trend":"buy"},"timestamp":1557719328000,"datetime":"2019-05-13T03:48:48.000Z","symbol":"BTC/UAH","price":186160,"amount":0.006249},{"id":"2427169","info":{"id":2427169,"price":"186533.0","volume":"0.001078","funds":"201.082574","market":"btcuah","created_at":"2019-05-13T03:48:49Z","side":null,"trend":"buy"},"timestamp":1557719329000,"datetime":"2019-05-13T03:48:49.000Z","symbol":"BTC/UAH","price":186533,"amount":0.001078},{"id":"2427170","info":{"id":2427170,"price":"186534.0","volume":"0.001418","funds":"264.505212","market":"btcuah","created_at":"2019-05-13T03:48:49Z","side":null,"trend":"buy"},"timestamp":1557719329000,"datetime":"2019-05-13T03:48:49.000Z","symbol":"BTC/UAH","price":186534,"amount":0.001418},{"id":"2427172","info":{"id":2427172,"price":"185000.0","volume":"0.002","funds":"370.0","market":"btcuah","created_at":"2019-05-13T03:56:46Z","side":null,"trend":"sell"},"timestamp":1557719806000,"datetime":"2019-05-13T03:56:46.000Z","symbol":"BTC/UAH","price":185000,"amount":0.002},{"id":"2427174","info":{"id":2427174,"price":"185000.0","volume":"0.001189","funds":"219.965","market":"btcuah","created_at":"2019-05-13T03:57:22Z","side":null,"trend":"sell"},"timestamp":1557719842000,"datetime":"2019-05-13T03:57:22.000Z","symbol":"BTC/UAH","price":185000,"amount":0.001189},{"id":"2427177","info":{"id":2427177,"price":"186592.0","volume":"0.000998","funds":"186.218816","market":"btcuah","created_at":"2019-05-13T04:01:22Z","side":null,"trend":"buy"},"timestamp":1557720082000,"datetime":"2019-05-13T04:01:22.000Z","symbol":"BTC/UAH","price":186592,"amount":0.000998},{"id":"2427178","info":{"id":2427178,"price":"186724.0","volume":"0.046666","funds":"8713.662184","market":"btcuah","created_at":"2019-05-13T04:01:22Z","side":null,"trend":"buy"},"timestamp":1557720082000,"datetime":"2019-05-13T04:01:22.000Z","symbol":"BTC/UAH","price":186724,"amount":0.046666},{"id":"2427179","info":{"id":2427179,"price":"185002.0","volume":"0.0043","funds":"795.5086","market":"btcuah","created_at":"2019-05-13T04:02:37Z","side":null,"trend":"sell"},"timestamp":1557720157000,"datetime":"2019-05-13T04:02:37.000Z","symbol":"BTC/UAH","price":185002,"amount":0.0043},{"id":"2427182","info":{"id":2427182,"price":"185004.0","volume":"0.0012","funds":"222.0048","market":"btcuah","created_at":"2019-05-13T04:02:45Z","side":null,"trend":"sell"},"timestamp":1557720165000,"datetime":"2019-05-13T04:02:45.000Z","symbol":"BTC/UAH","price":185004,"amount":0.0012},{"id":"2427184","info":{"id":2427184,"price":"185007.0","volume":"0.0079","funds":"1461.5553","market":"btcuah","created_at":"2019-05-13T04:02:53Z","side":null,"trend":"sell"},"timestamp":1557720173000,"datetime":"2019-05-13T04:02:53.000Z","symbol":"BTC/UAH","price":185007,"amount":0.0079},{"id":"2427187","info":{"id":2427187,"price":"185001.0","volume":"0.00189","funds":"349.65189","market":"btcuah","created_at":"2019-05-13T04:09:56Z","side":null,"trend":"sell"},"timestamp":1557720596000,"datetime":"2019-05-13T04:09:56.000Z","symbol":"BTC/UAH","price":185001,"amount":0.00189},{"id":"2427188","info":{"id":2427188,"price":"185000.0","volume":"0.003245","funds":"600.325","market":"btcuah","created_at":"2019-05-13T04:09:56Z","side":null,"trend":"sell"},"timestamp":1557720596000,"datetime":"2019-05-13T04:09:56.000Z","symbol":"BTC/UAH","price":185000,"amount":0.003245},{"id":"2427196","info":{"id":2427196,"price":"185013.0","volume":"0.013296","funds":"2459.932848","market":"btcuah","created_at":"2019-05-13T04:14:16Z","side":null,"trend":"buy"},"timestamp":1557720856000,"datetime":"2019-05-13T04:14:16.000Z","symbol":"BTC/UAH","price":185013,"amount":0.013296},{"id":"2427200","info":{"id":2427200,"price":"185029.0","volume":"0.019456","funds":"3599.924224","market":"btcuah","created_at":"2019-05-13T04:15:35Z","side":null,"trend":"sell"},"timestamp":1557720935000,"datetime":"2019-05-13T04:15:35.000Z","symbol":"BTC/UAH","price":185029,"amount":0.019456},{"id":"2427207","info":{"id":2427207,"price":"185093.0","volume":"0.005296","funds":"980.252528","market":"btcuah","created_at":"2019-05-13T04:21:14Z","side":null,"trend":"sell"},"timestamp":1557721274000,"datetime":"2019-05-13T04:21:14.000Z","symbol":"BTC/UAH","price":185093,"amount":0.005296},{"id":"2427211","info":{"id":2427211,"price":"185179.0","volume":"0.0047","funds":"870.3413","market":"btcuah","created_at":"2019-05-13T04:28:02Z","side":null,"trend":"sell"},"timestamp":1557721682000,"datetime":"2019-05-13T04:28:02.000Z","symbol":"BTC/UAH","price":185179,"amount":0.0047},{"id":"2427212","info":{"id":2427212,"price":"185198.0","volume":"0.011305","funds":"2093.66339","market":"btcuah","created_at":"2019-05-13T04:29:27Z","side":null,"trend":"sell"},"timestamp":1557721767000,"datetime":"2019-05-13T04:29:27.000Z","symbol":"BTC/UAH","price":185198,"amount":0.011305},{"id":"2427213","info":{"id":2427213,"price":"185197.0","volume":"0.003017","funds":"558.739349","market":"btcuah","created_at":"2019-05-13T04:29:28Z","side":null,"trend":"buy"},"timestamp":1557721768000,"datetime":"2019-05-13T04:29:28.000Z","symbol":"BTC/UAH","price":185197,"amount":0.003017},{"id":"2427215","info":{"id":2427215,"price":"185215.0","volume":"0.03162","funds":"5856.4983","market":"btcuah","created_at":"2019-05-13T04:30:47Z","side":null,"trend":"sell"},"timestamp":1557721847000,"datetime":"2019-05-13T04:30:47.000Z","symbol":"BTC/UAH","price":185215,"amount":0.03162},{"id":"2427231","info":{"id":2427231,"price":"185012.0","volume":"0.002699","funds":"499.347388","market":"btcuah","created_at":"2019-05-13T04:39:31Z","side":null,"trend":"sell"},"timestamp":1557722371000,"datetime":"2019-05-13T04:39:31.000Z","symbol":"BTC/UAH","price":185012,"amount":0.002699},{"id":"2427237","info":{"id":2427237,"price":"185060.0","volume":"0.00027","funds":"49.9662","market":"btcuah","created_at":"2019-05-13T04:43:49Z","side":null,"trend":"sell"},"timestamp":1557722629000,"datetime":"2019-05-13T04:43:49.000Z","symbol":"BTC/UAH","price":185060,"amount":0.00027},{"id":"2427239","info":{"id":2427239,"price":"185075.0","volume":"0.006483","funds":"1199.841225","market":"btcuah","created_at":"2019-05-13T04:44:47Z","side":null,"trend":"sell"},"timestamp":1557722687000,"datetime":"2019-05-13T04:44:47.000Z","symbol":"BTC/UAH","price":185075,"amount":0.006483},{"id":"2427245","info":{"id":2427245,"price":"185089.0","volume":"0.01052","funds":"1947.13628","market":"btcuah","created_at":"2019-05-13T04:45:56Z","side":null,"trend":"sell"},"timestamp":1557722756000,"datetime":"2019-05-13T04:45:56.000Z","symbol":"BTC/UAH","price":185089,"amount":0.01052},{"id":"2427244","info":{"id":2427244,"price":"185090.0","volume":"0.017574","funds":"3252.77166","market":"btcuah","created_at":"2019-05-13T04:45:56Z","side":null,"trend":"sell"},"timestamp":1557722756000,"datetime":"2019-05-13T04:45:56.000Z","symbol":"BTC/UAH","price":185090,"amount":0.017574},{"id":"2427249","info":{"id":2427249,"price":"185126.0","volume":"0.018009","funds":"3333.934134","market":"btcuah","created_at":"2019-05-13T04:49:10Z","side":null,"trend":"buy"},"timestamp":1557722950000,"datetime":"2019-05-13T04:49:10.000Z","symbol":"BTC/UAH","price":185126,"amount":0.018009},{"id":"2427250","info":{"id":2427250,"price":"185125.0","volume":"0.006376","funds":"1180.357","market":"btcuah","created_at":"2019-05-13T04:49:10Z","side":null,"trend":"sell"},"timestamp":1557722950000,"datetime":"2019-05-13T04:49:10.000Z","symbol":"BTC/UAH","price":185125,"amount":0.006376},{"id":"2427252","info":{"id":2427252,"price":"185126.0","volume":"0.034895","funds":"6459.97177","market":"btcuah","created_at":"2019-05-13T04:49:16Z","side":null,"trend":"sell"},"timestamp":1557722956000,"datetime":"2019-05-13T04:49:16.000Z","symbol":"BTC/UAH","price":185126,"amount":0.034895},{"id":"2427256","info":{"id":2427256,"price":"185126.0","volume":"0.015736","funds":"2913.142736","market":"btcuah","created_at":"2019-05-13T04:49:20Z","side":null,"trend":"buy"},"timestamp":1557722960000,"datetime":"2019-05-13T04:49:20.000Z","symbol":"BTC/UAH","price":185126,"amount":0.015736},{"id":"2427255","info":{"id":2427255,"price":"185126.0","volume":"0.019159","funds":"3546.829034","market":"btcuah","created_at":"2019-05-13T04:49:20Z","side":null,"trend":"sell"},"timestamp":1557722960000,"datetime":"2019-05-13T04:49:20.000Z","symbol":"BTC/UAH","price":185126,"amount":0.019159},{"id":"2427260","info":{"id":2427260,"price":"185089.0","volume":"0.00054","funds":"99.94806","market":"btcuah","created_at":"2019-05-13T04:49:48Z","side":null,"trend":"sell"},"timestamp":1557722988000,"datetime":"2019-05-13T04:49:48.000Z","symbol":"BTC/UAH","price":185089,"amount":0.00054},{"id":"2427264","info":{"id":2427264,"price":"185000.0","volume":"0.007469","funds":"1381.765","market":"btcuah","created_at":"2019-05-13T04:50:02Z","side":null,"trend":"sell"},"timestamp":1557723002000,"datetime":"2019-05-13T04:50:02.000Z","symbol":"BTC/UAH","price":185000,"amount":0.007469},{"id":"2427266","info":{"id":2427266,"price":"186714.0","volume":"0.008435","funds":"1574.93259","market":"btcuah","created_at":"2019-05-13T04:50:04Z","side":null,"trend":"buy"},"timestamp":1557723004000,"datetime":"2019-05-13T04:50:04.000Z","symbol":"BTC/UAH","price":186714,"amount":0.008435},{"id":"2427271","info":{"id":2427271,"price":"185001.0","volume":"0.002","funds":"370.002","market":"btcuah","created_at":"2019-05-13T04:51:01Z","side":null,"trend":"sell"},"timestamp":1557723061000,"datetime":"2019-05-13T04:51:01.000Z","symbol":"BTC/UAH","price":185001,"amount":0.002},{"id":"2427272","info":{"id":2427272,"price":"185000.0","volume":"0.009262","funds":"1713.47","market":"btcuah","created_at":"2019-05-13T04:51:01Z","side":null,"trend":"sell"},"timestamp":1557723061000,"datetime":"2019-05-13T04:51:01.000Z","symbol":"BTC/UAH","price":185000,"amount":0.009262},{"id":"2427273","info":{"id":2427273,"price":"185000.0","volume":"0.000138","funds":"25.53","market":"btcuah","created_at":"2019-05-13T04:51:01Z","side":null,"trend":"buy"},"timestamp":1557723061000,"datetime":"2019-05-13T04:51:01.000Z","symbol":"BTC/UAH","price":185000,"amount":0.000138},{"id":"2427278","info":{"id":2427278,"price":"184961.0","volume":"0.000002","funds":"0.369922","market":"btcuah","created_at":"2019-05-13T04:51:26Z","side":null,"trend":"sell"},"timestamp":1557723086000,"datetime":"2019-05-13T04:51:26.000Z","symbol":"BTC/UAH","price":184961,"amount":0.000002},{"id":"2427279","info":{"id":2427279,"price":"184888.0","volume":"0.010872","funds":"2010.102336","market":"btcuah","created_at":"2019-05-13T04:51:27Z","side":null,"trend":"sell"},"timestamp":1557723087000,"datetime":"2019-05-13T04:51:27.000Z","symbol":"BTC/UAH","price":184888,"amount":0.010872},{"id":"2427280","info":{"id":2427280,"price":"184888.0","volume":"0.027349","funds":"5056.501912","market":"btcuah","created_at":"2019-05-13T04:51:27Z","side":null,"trend":"buy"},"timestamp":1557723087000,"datetime":"2019-05-13T04:51:27.000Z","symbol":"BTC/UAH","price":184888,"amount":0.027349},{"id":"2427282","info":{"id":2427282,"price":"184679.0","volume":"0.00201","funds":"371.20479","market":"btcuah","created_at":"2019-05-13T04:52:51Z","side":null,"trend":"sell"},"timestamp":1557723171000,"datetime":"2019-05-13T04:52:51.000Z","symbol":"BTC/UAH","price":184679,"amount":0.00201},{"id":"2427283","info":{"id":2427283,"price":"184678.0","volume":"0.004611","funds":"851.550258","market":"btcuah","created_at":"2019-05-13T04:52:51Z","side":null,"trend":"sell"},"timestamp":1557723171000,"datetime":"2019-05-13T04:52:51.000Z","symbol":"BTC/UAH","price":184678,"amount":0.004611},{"id":"2427284","info":{"id":2427284,"price":"184615.0","volume":"0.000043","funds":"7.938445","market":"btcuah","created_at":"2019-05-13T04:52:51Z","side":null,"trend":"sell"},"timestamp":1557723171000,"datetime":"2019-05-13T04:52:51.000Z","symbol":"BTC/UAH","price":184615,"amount":0.000043},{"id":"2427287","info":{"id":2427287,"price":"184530.0","volume":"0.000048","funds":"8.85744","market":"btcuah","created_at":"2019-05-13T04:52:52Z","side":null,"trend":"sell"},"timestamp":1557723172000,"datetime":"2019-05-13T04:52:52.000Z","symbol":"BTC/UAH","price":184530,"amount":0.000048},{"id":"2427285","info":{"id":2427285,"price":"184540.0","volume":"0.000001","funds":"0.18454","market":"btcuah","created_at":"2019-05-13T04:52:52Z","side":null,"trend":"sell"},"timestamp":1557723172000,"datetime":"2019-05-13T04:52:52.000Z","symbol":"BTC/UAH","price":184540,"amount":0.000001},{"id":"2427286","info":{"id":2427286,"price":"184537.0","volume":"0.00019","funds":"35.06203","market":"btcuah","created_at":"2019-05-13T04:52:52Z","side":null,"trend":"sell"},"timestamp":1557723172000,"datetime":"2019-05-13T04:52:52.000Z","symbol":"BTC/UAH","price":184537,"amount":0.00019},{"id":"2427288","info":{"id":2427288,"price":"183328.0","volume":"0.009996","funds":"1832.546688","market":"btcuah","created_at":"2019-05-13T04:52:52Z","side":null,"trend":"sell"},"timestamp":1557723172000,"datetime":"2019-05-13T04:52:52.000Z","symbol":"BTC/UAH","price":183328,"amount":0.009996}]}}